{ "SolutionInfo": { "Status": 2, "Runtime": 2.1589999198913574e+00, "Work": 1.3696760703378308e+00, "ObjVal": 1290985, "ObjBound": 1290985, "ObjBoundC": 1290985, "MIPGap": 0, "IntVio": 0, "BoundVio": 0, "ConstrVio": 0, "IterCount": 1881, "BarIterCount": 0, "NodeCount": 1, "SolCount": 3, "PoolObjBound": 1290985, "PoolObjVal": [ 1290985, 1129850, 1048672]}, "Vars": [ { "VarName": "x[0]", "X": 1}, { "VarName": "x[1]", "X": 1}, { "VarName": "x[2]", "X": 1}, { "VarName": "x[3]", "X": 1}, { "VarName": "x[4]", "X": 1}, { "VarName": "x[5]", "X": 1}, { "VarName": "x[6]", "X": 1}, { "VarName": "x[7]", "X": 1}, { "VarName": "x[8]", "X": 1}, { "VarName": "x[9]", "X": 1}, { "VarName": "x[10]", "X": 1}, { "VarName": "x[11]", "X": 1}, { "VarName": "x[12]", "X": 1}, { "VarName": "x[13]", "X": 1}, { "VarName": "x[14]", "X": 1}, { "VarName": "x[15]", "X": 1}, { "VarName": "x[16]", "X": 1}, { "VarName": "x[17]", "X": 1}, { "VarName": "x[18]", "X": 1}, { "VarName": "x[19]", "X": 1}, { "VarName": "x[20]", "X": 1}, { "VarName": "x[21]", "X": 1}, { "VarName": "x[22]", "X": 1}, { "VarName": "x[23]", "X": 1}, { "VarName": "x[24]", "X": 1}, { "VarName": "x[25]", "X": 1}, { "VarName": "x[26]", "X": 1}, { "VarName": "x[27]", "X": 1}, { "VarName": "x[28]", "X": 1}, { "VarName": "x[29]", "X": 1}, { "VarName": "x[30]", "X": 1}, { "VarName": "x[31]", "X": 1}, { "VarName": "x[32]", "X": 1}, { "VarName": "x[33]", "X": 1}, { "VarName": "x[34]", "X": 1}, { "VarName": "x[35]", "X": 1}, { "VarName": "x[36]", "X": 1}, { "VarName": "x[37]", "X": 1}, { "VarName": "x[38]", "X": 1}, { "VarName": "x[39]", "X": 1}, { "VarName": "x[40]", "X": 1}, { "VarName": "x[41]", "X": 1}, { "VarName": "x[42]", "X": 1}, { "VarName": "x[43]", "X": 1}, { "VarName": "x[44]", "X": 1}, { "VarName": "x[45]", "X": 1}, { "VarName": "x[46]", "X": 1}, { "VarName": "x[47]", "X": 1}, { "VarName": "x[48]", "X": 1}, { "VarName": "x[49]", "X": 1}, { "VarName": "x[50]", "X": 1}, { "VarName": "x[51]", "X": 1}, { "VarName": "x[52]", "X": 1}, { "VarName": "x[53]", "X": 1}, { "VarName": "x[54]", "X": 1}, { "VarName": "x[55]", "X": 1}, { "VarName": "x[56]", "X": 1}, { "VarName": "x[57]", "X": 1}, { "VarName": "x[58]", "X": 1}, { "VarName": "x[59]", "X": 1}, { "VarName": "x[60]", "X": 1}, { "VarName": "x[61]", "X": 1}, { "VarName": "x[62]", "X": 1}, { "VarName": "x[63]", "X": 1}, { "VarName": "x[64]", "X": 1}, { "VarName": "x[65]", "X": 1}, { "VarName": "x[66]", "X": 1}, { "VarName": "x[67]", "X": 1}, { "VarName": "x[68]", "X": 1}, { "VarName": "x[69]", "X": 1}, { "VarName": "x[70]", "X": 1}, { "VarName": "x[71]", "X": 1}, { "VarName": "x[72]", "X": 1}, { "VarName": "x[73]", "X": 1}, { "VarName": "x[74]", "X": 1}, { "VarName": "x[75]", "X": 1}, { "VarName": "x[76]", "X": 1}, { "VarName": "x[77]", "X": 1}, { "VarName": "x[78]", "X": 1}, { "VarName": "x[79]", "X": 1}, { "VarName": "x[80]", "X": 1}, { "VarName": "x[81]", "X": 1}, { "VarName": "x[82]", "X": 1}, { "VarName": "x[83]", "X": 1}, { "VarName": "x[84]", "X": 1}, { "VarName": "x[85]", "X": 1}, { "VarName": "x[86]", "X": 1}, { "VarName": "x[87]", "X": 1}, { "VarName": "x[88]", "X": 1}, { "VarName": "x[89]", "X": 1}, { "VarName": "x[90]", "X": 1}, { "VarName": "x[91]", "X": 1}, { "VarName": "x[92]", "X": 1}, { "VarName": "x[93]", "X": 1}, { "VarName": "x[94]", "X": 1}, { "VarName": "x[95]", "X": 1}, { "VarName": "x[96]", "X": 1}, { "VarName": "x[97]", "X": 1}, { "VarName": "x[98]", "X": 1}, { "VarName": "x[99]", "X": 1}, { "VarName": "x[100]", "X": 1}, { "VarName": "x[101]", "X": 1}, { "VarName": "x[102]", "X": 1}, { "VarName": "x[103]", "X": 1}, { "VarName": "x[104]", "X": 1}, { "VarName": "x[105]", "X": 1}, { "VarName": "x[106]", "X": 1}, { "VarName": "x[107]", "X": 1}, { "VarName": "x[108]", "X": 1}, { "VarName": "x[109]", "X": 1}, { "VarName": "x[110]", "X": 1}, { "VarName": "x[111]", "X": 1}, { "VarName": "x[112]", "X": 1}, { "VarName": "x[113]", "X": 1}, { "VarName": "x[114]", "X": 1}, { "VarName": "x[115]", "X": 1}, { "VarName": "x[116]", "X": 1}, { "VarName": "x[117]", "X": 1}, { "VarName": "x[118]", "X": 1}, { "VarName": "x[119]", "X": 1}, { "VarName": "x[120]", "X": 1}, { "VarName": "x[121]", "X": 1}, { "VarName": "x[122]", "X": 1}, { "VarName": "x[123]", "X": 1}, { "VarName": "x[124]", "X": 1}, { "VarName": "x[125]", "X": 1}, { "VarName": "x[126]", "X": 1}, { "VarName": "x[127]", "X": 1}, { "VarName": "x[128]", "X": 1}, { "VarName": "x[129]", "X": 1}, { "VarName": "x[130]", "X": 1}, { "VarName": "x[131]", "X": 1}, { "VarName": "x[132]", "X": 1}, { "VarName": "x[133]", "X": 1}, { "VarName": "x[134]", "X": 1}, { "VarName": "x[135]", "X": 1}, { "VarName": "x[136]", "X": 1}, { "VarName": "x[137]", "X": 1}, { "VarName": "x[138]", "X": 1}, { "VarName": "x[139]", "X": 1}, { "VarName": "x[140]", "X": 1}, { "VarName": "x[141]", "X": 1}, { "VarName": "x[142]", "X": 1}, { "VarName": "x[143]", "X": 1}, { "VarName": "x[144]", "X": 1}, { "VarName": "x[145]", "X": 1}, { "VarName": "x[146]", "X": 1}, { "VarName": "x[147]", "X": 1}, { "VarName": "x[148]", "X": 1}, { "VarName": "x[149]", "X": 1}, { "VarName": "x[150]", "X": 1}, { "VarName": "x[151]", "X": 1}, { "VarName": "x[152]", "X": 1}, { "VarName": "x[153]", "X": 1}, { "VarName": "x[154]", "X": 1}, { "VarName": "x[155]", "X": 1}, { "VarName": "x[156]", "X": 1}, { "VarName": "x[157]", "X": 1}, { "VarName": "x[158]", "X": 1}, { "VarName": "x[159]", "X": 1}, { "VarName": "x[160]", "X": 1}, { "VarName": "x[161]", "X": 1}, { "VarName": "x[162]", "X": 1}, { "VarName": "x[163]", "X": 1}, { "VarName": "x[164]", "X": 1}, { "VarName": "x[165]", "X": 1}, { "VarName": "x[166]", "X": 1}, { "VarName": "x[167]", "X": 1}, { "VarName": "x[168]", "X": 1}, { "VarName": "x[169]", "X": 1}, { "VarName": "x[170]", "X": 1}, { "VarName": "x[171]", "X": 1}, { "VarName": "x[172]", "X": 1}, { "VarName": "x[173]", "X": 1}, { "VarName": "x[174]", "X": 1}, { "VarName": "x[175]", "X": 1}, { "VarName": "x[176]", "X": 1}, { "VarName": "x[177]", "X": 1}, { "VarName": "x[178]", "X": 1}, { "VarName": "x[179]", "X": 1}, { "VarName": "x[180]", "X": 1}, { "VarName": "x[181]", "X": 1}, { "VarName": "x[182]", "X": 1}, { "VarName": "x[183]", "X": 1}, { "VarName": "x[184]", "X": 1}, { "VarName": "x[185]", "X": 1}, { "VarName": "x[186]", "X": 1}, { "VarName": "x[187]", "X": 1}, { "VarName": "x[188]", "X": 1}, { "VarName": "x[189]", "X": 1}, { "VarName": "x[190]", "X": 1}, { "VarName": "x[191]", "X": 1}, { "VarName": "x[192]", "X": 1}, { "VarName": "x[193]", "X": 1}, { "VarName": "x[194]", "X": 1}, { "VarName": "x[195]", "X": 1}, { "VarName": "x[196]", "X": 1}, { "VarName": "x[197]", "X": 1}, { "VarName": "x[198]", "X": 1}, { "VarName": "x[199]", "X": 1}, { "VarName": "x[200]", "X": 1}, { "VarName": "x[201]", "X": 1}, { "VarName": "x[202]", "X": 1}, { "VarName": "x[203]", "X": 1}, { "VarName": "x[204]", "X": 1}, { "VarName": "x[205]", "X": 1}, { "VarName": "x[206]", "X": 1}, { "VarName": "x[207]", "X": 1}, { "VarName": "x[208]", "X": 1}, { "VarName": "x[209]", "X": 1}, { "VarName": "x[210]", "X": 1}, { "VarName": "x[211]", "X": 1}, { "VarName": "x[212]", "X": 1}, { "VarName": "x[213]", "X": 1}, { "VarName": "x[214]", "X": 1}, { "VarName": "x[215]", "X": 1}, { "VarName": "x[216]", "X": 1}, { "VarName": "x[217]", "X": 1}, { "VarName": "x[218]", "X": 1}, { "VarName": "x[219]", "X": 1}, { "VarName": "y[0,6]", "X": 1}, { "VarName": "y[1,6]", "X": 1}, { "VarName": "y[2,6]", "X": 1}, { "VarName": "y[3,6]", "X": 1}, { "VarName": "y[4,6]", "X": 1}, { "VarName": "y[5,6]", "X": 1}, { "VarName": "y[6,0]", "X": 1}, { "VarName": "y[7,0]", "X": 1}, { "VarName": "y[8,0]", "X": 1}, { "VarName": "y[9,0]", "X": 1}, { "VarName": "y[10,0]", "X": 1}, { "VarName": "y[11,0]", "X": 1}, { "VarName": "y[12,0]", "X": 1}, { "VarName": "y[13,0]", "X": 1}, { "VarName": "y[14,0]", "X": 1}, { "VarName": "y[15,0]", "X": 1}, { "VarName": "y[16,0]", "X": 1}, { "VarName": "y[17,0]", "X": 1}, { "VarName": "y[18,0]", "X": 1}, { "VarName": "y[19,0]", "X": 1}, { "VarName": "y[20,0]", "X": 1}, { "VarName": "y[21,0]", "X": 1}, { "VarName": "y[22,0]", "X": 1}, { "VarName": "y[23,0]", "X": 1}, { "VarName": "y[24,0]", "X": 1}, { "VarName": "y[25,0]", "X": 1}, { "VarName": "y[26,0]", "X": 1}, { "VarName": "y[27,8]", "X": 1}, { "VarName": "y[28,8]", "X": 1}, { "VarName": "y[29,8]", "X": 1}, { "VarName": "y[30,8]", "X": 1}, { "VarName": "y[31,8]", "X": 1}, { "VarName": "y[32,8]", "X": 1}, { "VarName": "y[33,8]", "X": 1}, { "VarName": "y[34,0]", "X": 1}, { "VarName": "y[35,0]", "X": 1}, { "VarName": "y[36,0]", "X": 1}, { "VarName": "y[37,0]", "X": 1}, { "VarName": "y[38,0]", "X": 1}, { "VarName": "y[39,0]", "X": 1}, { "VarName": "y[40,0]", "X": 1}, { "VarName": "y[41,8]", "X": 1}, { "VarName": "y[42,8]", "X": 1}, { "VarName": "y[43,8]", "X": 1}, { "VarName": "y[44,8]", "X": 1}, { "VarName": "y[45,8]", "X": 1}, { "VarName": "y[46,8]", "X": 1}, { "VarName": "y[47,8]", "X": 1}, { "VarName": "y[48,0]", "X": 1}, { "VarName": "y[49,0]", "X": 1}, { "VarName": "y[50,0]", "X": 1}, { "VarName": "y[51,0]", "X": 1}, { "VarName": "y[52,0]", "X": 1}, { "VarName": "y[53,0]", "X": 1}, { "VarName": "y[54,0]", "X": 1}, { "VarName": "y[55,0]", "X": 1}, { "VarName": "y[56,0]", "X": 1}, { "VarName": "y[57,0]", "X": 1}, { "VarName": "y[58,0]", "X": 1}, { "VarName": "y[59,0]", "X": 1}, { "VarName": "y[60,0]", "X": 1}, { "VarName": "y[61,0]", "X": 1}, { "VarName": "y[62,0]", "X": 1}, { "VarName": "y[63,0]", "X": 1}, { "VarName": "y[64,0]", "X": 1}, { "VarName": "y[65,9]", "X": 1}, { "VarName": "y[66,9]", "X": 1}, { "VarName": "y[67,9]", "X": 1}, { "VarName": "y[68,9]", "X": 1}, { "VarName": "y[69,9]", "X": 1}, { "VarName": "y[70,9]", "X": 1}, { "VarName": "y[71,0]", "X": 1}, { "VarName": "y[72,0]", "X": 1}, { "VarName": "y[73,0]", "X": 1}, { "VarName": "y[74,0]", "X": 1}, { "VarName": "y[75,0]", "X": 1}, { "VarName": "y[76,9]", "X": 1}, { "VarName": "y[77,9]", "X": 1}, { "VarName": "y[78,9]", "X": 1}, { "VarName": "y[79,9]", "X": 1}, { "VarName": "y[80,9]", "X": 1}, { "VarName": "y[81,8]", "X": 1}, { "VarName": "y[82,8]", "X": 1}, { "VarName": "y[83,8]", "X": 1}, { "VarName": "y[84,8]", "X": 1}, { "VarName": "y[85,8]", "X": 1}, { "VarName": "y[86,8]", "X": 1}, { "VarName": "y[87,6]", "X": 1}, { "VarName": "y[88,6]", "X": 1}, { "VarName": "y[89,6]", "X": 1}, { "VarName": "y[90,6]", "X": 1}, { "VarName": "y[91,6]", "X": 1}, { "VarName": "y[92,6]", "X": 1}, { "VarName": "y[93,6]", "X": 1}, { "VarName": "y[94,6]", "X": 1}, { "VarName": "y[95,6]", "X": 1}, { "VarName": "y[96,6]", "X": 1}, { "VarName": "y[97,2]", "X": 1}, { "VarName": "y[98,2]", "X": 1}, { "VarName": "y[99,2]", "X": 1}, { "VarName": "y[100,2]", "X": 1}, { "VarName": "y[101,2]", "X": 1}, { "VarName": "y[102,2]", "X": 1}, { "VarName": "y[103,2]", "X": 1}, { "VarName": "y[104,6]", "X": 1}, { "VarName": "y[105,6]", "X": 1}, { "VarName": "y[106,6]", "X": 1}, { "VarName": "y[107,6]", "X": 1}, { "VarName": "y[108,6]", "X": 1}, { "VarName": "y[109,9]", "X": 1}, { "VarName": "y[110,9]", "X": 1}, { "VarName": "y[111,9]", "X": 1}, { "VarName": "y[112,9]", "X": 1}, { "VarName": "y[113,9]", "X": 1}, { "VarName": "y[114,9]", "X": 1}, { "VarName": "y[115,9]", "X": 1}, { "VarName": "y[116,9]", "X": 1}, { "VarName": "y[117,7]", "X": 1}, { "VarName": "y[118,7]", "X": 1}, { "VarName": "y[119,7]", "X": 1}, { "VarName": "y[120,7]", "X": 1}, { "VarName": "y[121,7]", "X": 1}, { "VarName": "y[122,7]", "X": 1}, { "VarName": "y[123,7]", "X": 1}, { "VarName": "y[124,7]", "X": 1}, { "VarName": "y[125,7]", "X": 1}, { "VarName": "y[126,7]", "X": 1}, { "VarName": "y[127,2]", "X": 1}, { "VarName": "y[128,2]", "X": 1}, { "VarName": "y[129,2]", "X": 1}, { "VarName": "y[130,2]", "X": 1}, { "VarName": "y[131,2]", "X": 1}, { "VarName": "y[132,2]", "X": 1}, { "VarName": "y[133,2]", "X": 1}, { "VarName": "y[134,2]", "X": 1}, { "VarName": "y[135,6]", "X": 1}, { "VarName": "y[136,6]", "X": 1}, { "VarName": "y[137,6]", "X": 1}, { "VarName": "y[138,6]", "X": 1}, { "VarName": "y[139,6]", "X": 1}, { "VarName": "y[140,6]", "X": 1}, { "VarName": "y[141,6]", "X": 1}, { "VarName": "y[142,6]", "X": 1}, { "VarName": "y[143,6]", "X": 1}, { "VarName": "y[144,6]", "X": 1}, { "VarName": "y[145,6]", "X": 1}, { "VarName": "y[146,6]", "X": 1}, { "VarName": "y[147,2]", "X": 1}, { "VarName": "y[148,2]", "X": 1}, { "VarName": "y[149,2]", "X": 1}, { "VarName": "y[150,2]", "X": 1}, { "VarName": "y[151,2]", "X": 1}, { "VarName": "y[152,2]", "X": 1}, { "VarName": "y[153,6]", "X": 1}, { "VarName": "y[154,6]", "X": 1}, { "VarName": "y[155,6]", "X": 1}, { "VarName": "y[156,6]", "X": 1}, { "VarName": "y[157,6]", "X": 1}, { "VarName": "y[158,4]", "X": 1}, { "VarName": "y[159,4]", "X": 1}, { "VarName": "y[160,4]", "X": 1}, { "VarName": "y[161,4]", "X": 1}, { "VarName": "y[162,4]", "X": 1}, { "VarName": "y[163,4]", "X": 1}, { "VarName": "y[164,8]", "X": 1}, { "VarName": "y[165,8]", "X": 1}, { "VarName": "y[166,8]", "X": 1}, { "VarName": "y[167,8]", "X": 1}, { "VarName": "y[168,8]", "X": 1}, { "VarName": "y[169,8]", "X": 1}, { "VarName": "y[170,6]", "X": 1}, { "VarName": "y[171,6]", "X": 1}, { "VarName": "y[172,6]", "X": 1}, { "VarName": "y[173,6]", "X": 1}, { "VarName": "y[174,6]", "X": 1}, { "VarName": "y[175,6]", "X": 1}, { "VarName": "y[176,8]", "X": 1}, { "VarName": "y[177,8]", "X": 1}, { "VarName": "y[178,8]", "X": 1}, { "VarName": "y[179,8]", "X": 1}, { "VarName": "y[180,8]", "X": 1}, { "VarName": "y[181,8]", "X": 1}, { "VarName": "y[182,8]", "X": 1}, { "VarName": "y[183,9]", "X": 1}, { "VarName": "y[184,9]", "X": 1}, { "VarName": "y[185,9]", "X": 1}, { "VarName": "y[186,9]", "X": 1}, { "VarName": "y[187,9]", "X": 1}, { "VarName": "y[188,9]", "X": 1}, { "VarName": "y[189,9]", "X": 1}, { "VarName": "y[190,9]", "X": 1}, { "VarName": "y[191,9]", "X": 1}, { "VarName": "y[192,4]", "X": 1}, { "VarName": "y[193,4]", "X": 1}, { "VarName": "y[194,4]", "X": 1}, { "VarName": "y[195,4]", "X": 1}, { "VarName": "y[196,4]", "X": 1}, { "VarName": "y[197,9]", "X": 1}, { "VarName": "y[198,9]", "X": 1}, { "VarName": "y[199,9]", "X": 1}, { "VarName": "y[200,9]", "X": 1}, { "VarName": "y[201,9]", "X": 1}, { "VarName": "y[202,9]", "X": 1}, { "VarName": "y[203,9]", "X": 1}, { "VarName": "y[204,9]", "X": 1}, { "VarName": "y[205,9]", "X": 1}, { "VarName": "y[206,9]", "X": 1}, { "VarName": "y[207,9]", "X": 1}, { "VarName": "y[208,9]", "X": 1}, { "VarName": "y[209,9]", "X": 1}, { "VarName": "y[210,9]", "X": 1}, { "VarName": "y[211,9]", "X": 1}, { "VarName": "y[212,1]", "X": 1}, { "VarName": "y[213,1]", "X": 1}, { "VarName": "y[214,1]", "X": 1}, { "VarName": "y[215,1]", "X": 1}, { "VarName": "y[216,1]", "X": 1}, { "VarName": "y[217,1]", "X": 1}, { "VarName": "y[218,1]", "X": 1}, { "VarName": "y[219,1]", "X": 1}, { "VarName": "y[220,1]", "X": 1}, { "VarName": "y[221,8]", "X": 1}, { "VarName": "y[222,8]", "X": 1}, { "VarName": "y[223,8]", "X": 1}, { "VarName": "y[224,8]", "X": 1}, { "VarName": "y[225,8]", "X": 1}, { "VarName": "y[226,2]", "X": 1}, { "VarName": "y[227,2]", "X": 1}, { "VarName": "y[228,2]", "X": 1}, { "VarName": "y[229,2]", "X": 1}, { "VarName": "y[230,2]", "X": 1}, { "VarName": "y[231,2]", "X": 1}, { "VarName": "y[232,2]", "X": 1}, { "VarName": "y[233,5]", "X": 1}, { "VarName": "y[234,5]", "X": 1}, { "VarName": "y[235,5]", "X": 1}, { "VarName": "y[236,5]", "X": 1}, { "VarName": "y[237,5]", "X": 1}, { "VarName": "y[238,5]", "X": 1}, { "VarName": "y[239,5]", "X": 1}, { "VarName": "y[240,5]", "X": 1}, { "VarName": "y[241,5]", "X": 1}, { "VarName": "y[242,9]", "X": 1}, { "VarName": "y[243,9]", "X": 1}, { "VarName": "y[244,9]", "X": 1}, { "VarName": "y[245,9]", "X": 1}, { "VarName": "y[246,9]", "X": 1}, { "VarName": "y[247,9]", "X": 1}, { "VarName": "y[248,4]", "X": 1}, { "VarName": "y[249,4]", "X": 1}, { "VarName": "y[250,4]", "X": 1}, { "VarName": "y[251,4]", "X": 1}, { "VarName": "y[252,4]", "X": 1}, { "VarName": "y[253,4]", "X": 1}, { "VarName": "y[254,4]", "X": 1}, { "VarName": "y[255,4]", "X": 1}, { "VarName": "y[256,4]", "X": 1}, { "VarName": "y[257,4]", "X": 1}, { "VarName": "y[258,1]", "X": 1}, { "VarName": "y[259,1]", "X": 1}, { "VarName": "y[260,1]", "X": 1}, { "VarName": "y[261,1]", "X": 1}, { "VarName": "y[262,1]", "X": 1}, { "VarName": "y[263,1]", "X": 1}, { "VarName": "y[264,1]", "X": 1}, { "VarName": "y[265,1]", "X": 1}, { "VarName": "y[266,1]", "X": 1}, { "VarName": "y[267,1]", "X": 1}, { "VarName": "y[268,4]", "X": 1}, { "VarName": "y[269,4]", "X": 1}, { "VarName": "y[270,4]", "X": 1}, { "VarName": "y[271,4]", "X": 1}, { "VarName": "y[272,4]", "X": 1}, { "VarName": "y[273,4]", "X": 1}, { "VarName": "y[274,4]", "X": 1}, { "VarName": "y[275,6]", "X": 1}, { "VarName": "y[276,6]", "X": 1}, { "VarName": "y[277,6]", "X": 1}, { "VarName": "y[278,6]", "X": 1}, { "VarName": "y[279,6]", "X": 1}, { "VarName": "y[280,6]", "X": 1}, { "VarName": "y[281,6]", "X": 1}, { "VarName": "y[282,6]", "X": 1}, { "VarName": "y[283,6]", "X": 1}, { "VarName": "y[284,6]", "X": 1}, { "VarName": "y[285,6]", "X": 1}, { "VarName": "y[286,6]", "X": 1}, { "VarName": "y[287,6]", "X": 1}, { "VarName": "y[288,6]", "X": 1}, { "VarName": "y[289,6]", "X": 1}, { "VarName": "y[290,7]", "X": 1}, { "VarName": "y[291,7]", "X": 1}, { "VarName": "y[292,7]", "X": 1}, { "VarName": "y[293,7]", "X": 1}, { "VarName": "y[294,7]", "X": 1}, { "VarName": "y[295,7]", "X": 1}, { "VarName": "y[296,2]", "X": 1}, { "VarName": "y[297,2]", "X": 1}, { "VarName": "y[298,2]", "X": 1}, { "VarName": "y[299,2]", "X": 1}, { "VarName": "y[300,2]", "X": 1}, { "VarName": "y[301,2]", "X": 1}, { "VarName": "y[302,2]", "X": 1}, { "VarName": "y[303,2]", "X": 1}, { "VarName": "y[304,7]", "X": 1}, { "VarName": "y[305,7]", "X": 1}, { "VarName": "y[306,7]", "X": 1}, { "VarName": "y[307,7]", "X": 1}, { "VarName": "y[308,7]", "X": 1}, { "VarName": "y[309,7]", "X": 1}, { "VarName": "y[310,7]", "X": 1}, { "VarName": "y[311,7]", "X": 1}, { "VarName": "y[312,7]", "X": 1}, { "VarName": "y[313,7]", "X": 1}, { "VarName": "y[314,7]", "X": 1}, { "VarName": "y[315,7]", "X": 1}, { "VarName": "y[316,7]", "X": 1}, { "VarName": "y[317,7]", "X": 1}, { "VarName": "y[318,7]", "X": 1}, { "VarName": "y[319,7]", "X": 1}, { "VarName": "y[320,4]", "X": 1}, { "VarName": "y[321,4]", "X": 1}, { "VarName": "y[322,4]", "X": 1}, { "VarName": "y[323,4]", "X": 1}, { "VarName": "y[324,4]", "X": 1}, { "VarName": "y[325,4]", "X": 1}, { "VarName": "y[326,2]", "X": 1}, { "VarName": "y[327,2]", "X": 1}, { "VarName": "y[328,2]", "X": 1}, { "VarName": "y[329,2]", "X": 1}, { "VarName": "y[330,2]", "X": 1}, { "VarName": "y[331,2]", "X": 1}, { "VarName": "y[332,2]", "X": 1}, { "VarName": "y[333,2]", "X": 1}, { "VarName": "y[334,2]", "X": 1}, { "VarName": "y[335,8]", "X": 1}, { "VarName": "y[336,8]", "X": 1}, { "VarName": "y[337,8]", "X": 1}, { "VarName": "y[338,8]", "X": 1}, { "VarName": "y[339,8]", "X": 1}, { "VarName": "y[340,8]", "X": 1}, { "VarName": "y[341,8]", "X": 1}, { "VarName": "y[342,8]", "X": 1}, { "VarName": "y[343,2]", "X": 1}, { "VarName": "y[344,2]", "X": 1}, { "VarName": "y[345,2]", "X": 1}, { "VarName": "y[346,2]", "X": 1}, { "VarName": "y[347,2]", "X": 1}, { "VarName": "y[348,2]", "X": 1}, { "VarName": "y[349,4]", "X": 1}, { "VarName": "y[350,4]", "X": 1}, { "VarName": "y[351,4]", "X": 1}, { "VarName": "y[352,4]", "X": 1}, { "VarName": "y[353,4]", "X": 1}, { "VarName": "y[354,4]", "X": 1}, { "VarName": "y[355,4]", "X": 1}, { "VarName": "y[356,4]", "X": 1}, { "VarName": "y[357,8]", "X": 1}, { "VarName": "y[358,8]", "X": 1}, { "VarName": "y[359,8]", "X": 1}, { "VarName": "y[360,8]", "X": 1}, { "VarName": "y[361,8]", "X": 1}, { "VarName": "y[362,3]", "X": 1}, { "VarName": "y[363,3]", "X": 1}, { "VarName": "y[364,3]", "X": 1}, { "VarName": "y[365,3]", "X": 1}, { "VarName": "y[366,3]", "X": 1}, { "VarName": "y[367,0]", "X": 1}, { "VarName": "y[368,0]", "X": 1}, { "VarName": "y[369,0]", "X": 1}, { "VarName": "y[370,0]", "X": 1}, { "VarName": "y[371,0]", "X": 1}, { "VarName": "y[372,0]", "X": 1}, { "VarName": "y[373,0]", "X": 1}, { "VarName": "y[374,0]", "X": 1}, { "VarName": "y[375,0]", "X": 1}, { "VarName": "y[376,1]", "X": 1}, { "VarName": "y[377,1]", "X": 1}, { "VarName": "y[378,1]", "X": 1}, { "VarName": "y[379,1]", "X": 1}, { "VarName": "y[380,1]", "X": 1}, { "VarName": "y[381,9]", "X": 1}, { "VarName": "y[382,9]", "X": 1}, { "VarName": "y[383,9]", "X": 1}, { "VarName": "y[384,9]", "X": 1}, { "VarName": "y[385,9]", "X": 1}, { "VarName": "y[386,9]", "X": 1}, { "VarName": "y[387,9]", "X": 1}, { "VarName": "y[388,9]", "X": 1}, { "VarName": "y[389,9]", "X": 1}, { "VarName": "y[390,9]", "X": 1}, { "VarName": "y[391,9]", "X": 1}, { "VarName": "y[392,9]", "X": 1}, { "VarName": "y[393,9]", "X": 1}, { "VarName": "y[394,9]", "X": 1}, { "VarName": "y[395,9]", "X": 1}, { "VarName": "y[396,9]", "X": 1}, { "VarName": "y[397,9]", "X": 1}, { "VarName": "y[398,7]", "X": 1}, { "VarName": "y[399,7]", "X": 1}, { "VarName": "y[400,7]", "X": 1}, { "VarName": "y[401,7]", "X": 1}, { "VarName": "y[402,7]", "X": 1}, { "VarName": "y[403,7]", "X": 1}, { "VarName": "y[404,7]", "X": 1}, { "VarName": "y[405,7]", "X": 1}, { "VarName": "y[406,3]", "X": 1}, { "VarName": "y[407,3]", "X": 1}, { "VarName": "y[408,3]", "X": 1}, { "VarName": "y[409,3]", "X": 1}, { "VarName": "y[410,3]", "X": 1}, { "VarName": "y[411,3]", "X": 1}, { "VarName": "y[412,6]", "X": 1}, { "VarName": "y[413,6]", "X": 1}, { "VarName": "y[414,6]", "X": 1}, { "VarName": "y[415,6]", "X": 1}, { "VarName": "y[416,6]", "X": 1}, { "VarName": "y[417,6]", "X": 1}, { "VarName": "y[418,6]", "X": 1}, { "VarName": "y[419,6]", "X": 1}, { "VarName": "y[420,6]", "X": 1}, { "VarName": "y[421,2]", "X": 1}, { "VarName": "y[422,2]", "X": 1}, { "VarName": "y[423,2]", "X": 1}, { "VarName": "y[424,2]", "X": 1}, { "VarName": "y[425,2]", "X": 1}, { "VarName": "y[426,2]", "X": 1}, { "VarName": "y[427,2]", "X": 1}, { "VarName": "y[428,2]", "X": 1}, { "VarName": "y[429,0]", "X": 1}, { "VarName": "y[430,0]", "X": 1}, { "VarName": "y[431,0]", "X": 1}, { "VarName": "y[432,0]", "X": 1}, { "VarName": "y[433,0]", "X": 1}, { "VarName": "y[434,0]", "X": 1}, { "VarName": "y[435,0]", "X": 1}, { "VarName": "y[436,6]", "X": 1}, { "VarName": "y[437,6]", "X": 1}, { "VarName": "y[438,6]", "X": 1}, { "VarName": "y[439,6]", "X": 1}, { "VarName": "y[440,6]", "X": 1}, { "VarName": "y[441,6]", "X": 1}, { "VarName": "y[442,6]", "X": 1}, { "VarName": "y[443,6]", "X": 1}, { "VarName": "y[444,6]", "X": 1}, { "VarName": "y[445,6]", "X": 1}, { "VarName": "y[446,6]", "X": 1}, { "VarName": "y[447,6]", "X": 1}, { "VarName": "y[448,6]", "X": 1}, { "VarName": "y[449,6]", "X": 1}, { "VarName": "y[450,6]", "X": 1}, { "VarName": "y[451,6]", "X": 1}, { "VarName": "y[452,6]", "X": 1}, { "VarName": "y[453,2]", "X": 1}, { "VarName": "y[454,2]", "X": 1}, { "VarName": "y[455,2]", "X": 1}, { "VarName": "y[456,2]", "X": 1}, { "VarName": "y[457,2]", "X": 1}, { "VarName": "y[458,2]", "X": 1}, { "VarName": "y[459,2]", "X": 1}, { "VarName": "y[460,8]", "X": 1}, { "VarName": "y[461,8]", "X": 1}, { "VarName": "y[462,8]", "X": 1}, { "VarName": "y[463,8]", "X": 1}, { "VarName": "y[464,8]", "X": 1}, { "VarName": "y[465,8]", "X": 1}, { "VarName": "y[466,8]", "X": 1}, { "VarName": "y[467,8]", "X": 1}, { "VarName": "y[468,8]", "X": 1}, { "VarName": "y[469,8]", "X": 1}, { "VarName": "y[470,3]", "X": 1}, { "VarName": "y[471,3]", "X": 1}, { "VarName": "y[472,3]", "X": 1}, { "VarName": "y[473,3]", "X": 1}, { "VarName": "y[474,3]", "X": 1}, { "VarName": "y[475,3]", "X": 1}, { "VarName": "y[476,3]", "X": 1}, { "VarName": "y[477,3]", "X": 1}, { "VarName": "y[478,3]", "X": 1}, { "VarName": "y[479,3]", "X": 1}, { "VarName": "y[480,5]", "X": 1}, { "VarName": "y[481,5]", "X": 1}, { "VarName": "y[482,5]", "X": 1}, { "VarName": "y[483,5]", "X": 1}, { "VarName": "y[484,5]", "X": 1}, { "VarName": "y[485,5]", "X": 1}, { "VarName": "y[486,5]", "X": 1}, { "VarName": "y[487,5]", "X": 1}, { "VarName": "y[488,5]", "X": 1}, { "VarName": "y[489,5]", "X": 1}, { "VarName": "y[490,9]", "X": 1}, { "VarName": "y[491,9]", "X": 1}, { "VarName": "y[492,9]", "X": 1}, { "VarName": "y[493,9]", "X": 1}, { "VarName": "y[494,9]", "X": 1}, { "VarName": "y[495,9]", "X": 1}, { "VarName": "y[496,9]", "X": 1}, { "VarName": "y[497,9]", "X": 1}, { "VarName": "y[498,9]", "X": 1}, { "VarName": "y[499,9]", "X": 1}, { "VarName": "y[500,7]", "X": 1}, { "VarName": "y[501,7]", "X": 1}, { "VarName": "y[502,7]", "X": 1}, { "VarName": "y[503,7]", "X": 1}, { "VarName": "y[504,7]", "X": 1}, { "VarName": "y[505,7]", "X": 1}, { "VarName": "y[506,7]", "X": 1}, { "VarName": "y[507,7]", "X": 1}, { "VarName": "y[508,7]", "X": 1}, { "VarName": "y[509,7]", "X": 1}, { "VarName": "y[510,7]", "X": 1}, { "VarName": "y[511,5]", "X": 1}, { "VarName": "y[512,5]", "X": 1}, { "VarName": "y[513,5]", "X": 1}, { "VarName": "y[514,5]", "X": 1}, { "VarName": "y[515,5]", "X": 1}, { "VarName": "y[516,5]", "X": 1}, { "VarName": "y[517,5]", "X": 1}, { "VarName": "y[518,5]", "X": 1}, { "VarName": "y[519,4]", "X": 1}, { "VarName": "y[520,4]", "X": 1}, { "VarName": "y[521,4]", "X": 1}, { "VarName": "y[522,4]", "X": 1}, { "VarName": "y[523,4]", "X": 1}, { "VarName": "y[524,4]", "X": 1}, { "VarName": "y[525,4]", "X": 1}, { "VarName": "y[526,6]", "X": 1}, { "VarName": "y[527,6]", "X": 1}, { "VarName": "y[528,6]", "X": 1}, { "VarName": "y[529,6]", "X": 1}, { "VarName": "y[530,6]", "X": 1}, { "VarName": "y[531,8]", "X": 1}, { "VarName": "y[532,8]", "X": 1}, { "VarName": "y[533,8]", "X": 1}, { "VarName": "y[534,8]", "X": 1}, { "VarName": "y[535,8]", "X": 1}, { "VarName": "y[536,8]", "X": 1}, { "VarName": "y[537,8]", "X": 1}, { "VarName": "y[538,9]", "X": 1}, { "VarName": "y[539,9]", "X": 1}, { "VarName": "y[540,9]", "X": 1}, { "VarName": "y[541,9]", "X": 1}, { "VarName": "y[542,9]", "X": 1}, { "VarName": "y[543,9]", "X": 1}, { "VarName": "y[544,9]", "X": 1}, { "VarName": "y[545,5]", "X": 1}, { "VarName": "y[546,5]", "X": 1}, { "VarName": "y[547,5]", "X": 1}, { "VarName": "y[548,5]", "X": 1}, { "VarName": "y[549,5]", "X": 1}, { "VarName": "y[550,6]", "X": 1}, { "VarName": "y[551,6]", "X": 1}, { "VarName": "y[552,6]", "X": 1}, { "VarName": "y[553,6]", "X": 1}, { "VarName": "y[554,6]", "X": 1}, { "VarName": "y[555,6]", "X": 1}, { "VarName": "y[556,6]", "X": 1}, { "VarName": "y[557,8]", "X": 1}, { "VarName": "y[558,8]", "X": 1}, { "VarName": "y[559,8]", "X": 1}, { "VarName": "y[560,8]", "X": 1}, { "VarName": "y[561,8]", "X": 1}, { "VarName": "y[562,8]", "X": 1}, { "VarName": "y[563,8]", "X": 1}, { "VarName": "y[564,6]", "X": 1}, { "VarName": "y[565,6]", "X": 1}, { "VarName": "y[566,6]", "X": 1}, { "VarName": "y[567,6]", "X": 1}, { "VarName": "y[568,6]", "X": 1}, { "VarName": "y[569,2]", "X": 1}, { "VarName": "y[570,2]", "X": 1}, { "VarName": "y[571,2]", "X": 1}, { "VarName": "y[572,2]", "X": 1}, { "VarName": "y[573,2]", "X": 1}, { "VarName": "y[574,2]", "X": 1}, { "VarName": "y[575,2]", "X": 1}, { "VarName": "y[576,2]", "X": 1}, { "VarName": "y[577,2]", "X": 1}, { "VarName": "y[578,2]", "X": 1}, { "VarName": "y[579,1]", "X": 1}, { "VarName": "y[580,1]", "X": 1}, { "VarName": "y[581,1]", "X": 1}, { "VarName": "y[582,1]", "X": 1}, { "VarName": "y[583,1]", "X": 1}, { "VarName": "y[584,4]", "X": 1}, { "VarName": "y[585,4]", "X": 1}, { "VarName": "y[586,4]", "X": 1}, { "VarName": "y[587,4]", "X": 1}, { "VarName": "y[588,4]", "X": 1}, { "VarName": "y[589,4]", "X": 1}, { "VarName": "y[590,4]", "X": 1}, { "VarName": "y[591,8]", "X": 1}, { "VarName": "y[592,8]", "X": 1}, { "VarName": "y[593,8]", "X": 1}, { "VarName": "y[594,8]", "X": 1}, { "VarName": "y[595,8]", "X": 1}, { "VarName": "y[596,8]", "X": 1}, { "VarName": "y[597,5]", "X": 1}, { "VarName": "y[598,5]", "X": 1}, { "VarName": "y[599,5]", "X": 1}, { "VarName": "y[600,5]", "X": 1}, { "VarName": "y[601,5]", "X": 1}, { "VarName": "y[602,5]", "X": 1}, { "VarName": "y[603,5]", "X": 1}, { "VarName": "y[604,5]", "X": 1}, { "VarName": "y[605,5]", "X": 1}, { "VarName": "y[606,5]", "X": 1}, { "VarName": "y[607,5]", "X": 1}, { "VarName": "y[608,5]", "X": 1}, { "VarName": "y[609,5]", "X": 1}, { "VarName": "y[610,5]", "X": 1}, { "VarName": "y[611,5]", "X": 1}, { "VarName": "y[612,5]", "X": 1}, { "VarName": "y[613,5]", "X": 1}, { "VarName": "y[614,5]", "X": 1}, { "VarName": "y[615,5]", "X": 1}, { "VarName": "y[616,5]", "X": 1}, { "VarName": "y[617,1]", "X": 1}, { "VarName": "y[618,1]", "X": 1}, { "VarName": "y[619,1]", "X": 1}, { "VarName": "y[620,1]", "X": 1}, { "VarName": "y[621,1]", "X": 1}, { "VarName": "y[622,1]", "X": 1}, { "VarName": "y[623,1]", "X": 1}, { "VarName": "y[624,1]", "X": 1}, { "VarName": "y[625,9]", "X": 1}, { "VarName": "y[626,9]", "X": 1}, { "VarName": "y[627,9]", "X": 1}, { "VarName": "y[628,9]", "X": 1}, { "VarName": "y[629,9]", "X": 1}, { "VarName": "y[630,9]", "X": 1}, { "VarName": "y[631,9]", "X": 1}, { "VarName": "y[632,9]", "X": 1}, { "VarName": "y[633,9]", "X": 1}, { "VarName": "y[634,9]", "X": 1}, { "VarName": "y[635,9]", "X": 1}, { "VarName": "y[636,9]", "X": 1}, { "VarName": "y[637,9]", "X": 1}, { "VarName": "y[638,9]", "X": 1}, { "VarName": "y[639,9]", "X": 1}, { "VarName": "y[640,9]", "X": 1}, { "VarName": "y[641,9]", "X": 1}, { "VarName": "y[642,9]", "X": 1}, { "VarName": "y[643,3]", "X": 1}, { "VarName": "y[644,3]", "X": 1}, { "VarName": "y[645,3]", "X": 1}, { "VarName": "y[646,3]", "X": 1}, { "VarName": "y[647,3]", "X": 1}, { "VarName": "y[648,3]", "X": 1}, { "VarName": "y[649,3]", "X": 1}, { "VarName": "y[650,3]", "X": 1}, { "VarName": "y[651,3]", "X": 1}, { "VarName": "y[652,5]", "X": 1}, { "VarName": "y[653,5]", "X": 1}, { "VarName": "y[654,5]", "X": 1}, { "VarName": "y[655,5]", "X": 1}, { "VarName": "y[656,5]", "X": 1}, { "VarName": "y[657,5]", "X": 1}, { "VarName": "y[658,5]", "X": 1}, { "VarName": "y[659,5]", "X": 1}, { "VarName": "y[660,5]", "X": 1}, { "VarName": "y[661,5]", "X": 1}, { "VarName": "y[662,4]", "X": 1}, { "VarName": "y[663,4]", "X": 1}, { "VarName": "y[664,4]", "X": 1}, { "VarName": "y[665,4]", "X": 1}, { "VarName": "y[666,4]", "X": 1}, { "VarName": "y[667,4]", "X": 1}, { "VarName": "y[668,7]", "X": 1}, { "VarName": "y[669,7]", "X": 1}, { "VarName": "y[670,7]", "X": 1}, { "VarName": "y[671,7]", "X": 1}, { "VarName": "y[672,7]", "X": 1}, { "VarName": "y[673,7]", "X": 1}, { "VarName": "y[674,7]", "X": 1}, { "VarName": "y[675,7]", "X": 1}, { "VarName": "y[676,7]", "X": 1}, { "VarName": "y[677,7]", "X": 1}, { "VarName": "y[678,8]", "X": 1}, { "VarName": "y[679,8]", "X": 1}, { "VarName": "y[680,8]", "X": 1}, { "VarName": "y[681,8]", "X": 1}, { "VarName": "y[682,8]", "X": 1}, { "VarName": "y[683,8]", "X": 1}, { "VarName": "y[684,8]", "X": 1}, { "VarName": "y[685,8]", "X": 1}, { "VarName": "y[686,6]", "X": 1}, { "VarName": "y[687,6]", "X": 1}, { "VarName": "y[688,6]", "X": 1}, { "VarName": "y[689,6]", "X": 1}, { "VarName": "y[690,6]", "X": 1}, { "VarName": "y[691,6]", "X": 1}, { "VarName": "y[692,6]", "X": 1}, { "VarName": "y[693,6]", "X": 1}, { "VarName": "y[694,6]", "X": 1}, { "VarName": "y[695,6]", "X": 1}, { "VarName": "y[696,6]", "X": 1}, { "VarName": "y[697,6]", "X": 1}, { "VarName": "y[698,6]", "X": 1}, { "VarName": "y[699,6]", "X": 1}, { "VarName": "y[700,6]", "X": 1}, { "VarName": "y[701,6]", "X": 1}, { "VarName": "y[702,6]", "X": 1}, { "VarName": "y[703,6]", "X": 1}, { "VarName": "y[704,6]", "X": 1}, { "VarName": "y[705,2]", "X": 1}, { "VarName": "y[706,2]", "X": 1}, { "VarName": "y[707,2]", "X": 1}, { "VarName": "y[708,2]", "X": 1}, { "VarName": "y[709,2]", "X": 1}, { "VarName": "y[710,2]", "X": 1}, { "VarName": "y[711,6]", "X": 1}, { "VarName": "y[712,6]", "X": 1}, { "VarName": "y[713,6]", "X": 1}, { "VarName": "y[714,6]", "X": 1}, { "VarName": "y[715,6]", "X": 1}, { "VarName": "y[716,6]", "X": 1}, { "VarName": "y[717,6]", "X": 1}, { "VarName": "y[718,1]", "X": 1}, { "VarName": "y[719,1]", "X": 1}, { "VarName": "y[720,1]", "X": 1}, { "VarName": "y[721,1]", "X": 1}, { "VarName": "y[722,1]", "X": 1}, { "VarName": "y[723,1]", "X": 1}, { "VarName": "y[724,1]", "X": 1}, { "VarName": "y[725,1]", "X": 1}, { "VarName": "y[726,1]", "X": 1}, { "VarName": "y[727,1]", "X": 1}, { "VarName": "y[728,5]", "X": 1}, { "VarName": "y[729,5]", "X": 1}, { "VarName": "y[730,5]", "X": 1}, { "VarName": "y[731,5]", "X": 1}, { "VarName": "y[732,5]", "X": 1}, { "VarName": "y[733,5]", "X": 1}, { "VarName": "y[734,5]", "X": 1}, { "VarName": "y[735,9]", "X": 1}, { "VarName": "y[736,9]", "X": 1}, { "VarName": "y[737,9]", "X": 1}, { "VarName": "y[738,9]", "X": 1}, { "VarName": "y[739,9]", "X": 1}, { "VarName": "y[740,4]", "X": 1}, { "VarName": "y[741,4]", "X": 1}, { "VarName": "y[742,4]", "X": 1}, { "VarName": "y[743,4]", "X": 1}, { "VarName": "y[744,4]", "X": 1}, { "VarName": "y[745,4]", "X": 1}, { "VarName": "y[746,8]", "X": 1}, { "VarName": "y[747,8]", "X": 1}, { "VarName": "y[748,8]", "X": 1}, { "VarName": "y[749,8]", "X": 1}, { "VarName": "y[750,8]", "X": 1}, { "VarName": "y[751,8]", "X": 1}, { "VarName": "y[752,8]", "X": 1}, { "VarName": "y[753,8]", "X": 1}, { "VarName": "y[754,8]", "X": 1}, { "VarName": "y[755,8]", "X": 1}, { "VarName": "y[756,3]", "X": 1}, { "VarName": "y[757,3]", "X": 1}, { "VarName": "y[758,3]", "X": 1}, { "VarName": "y[759,3]", "X": 1}, { "VarName": "y[760,3]", "X": 1}, { "VarName": "y[761,3]", "X": 1}, { "VarName": "y[762,3]", "X": 1}, { "VarName": "y[763,3]", "X": 1}, { "VarName": "y[764,9]", "X": 1}, { "VarName": "y[765,9]", "X": 1}, { "VarName": "y[766,9]", "X": 1}, { "VarName": "y[767,9]", "X": 1}, { "VarName": "y[768,9]", "X": 1}, { "VarName": "y[769,9]", "X": 1}, { "VarName": "y[770,9]", "X": 1}, { "VarName": "y[771,9]", "X": 1}, { "VarName": "y[772,9]", "X": 1}, { "VarName": "y[773,0]", "X": 1}, { "VarName": "y[774,0]", "X": 1}, { "VarName": "y[775,0]", "X": 1}, { "VarName": "y[776,0]", "X": 1}, { "VarName": "y[777,0]", "X": 1}, { "VarName": "y[778,0]", "X": 1}, { "VarName": "y[779,0]", "X": 1}, { "VarName": "y[780,0]", "X": 1}, { "VarName": "y[781,2]", "X": 1}, { "VarName": "y[782,2]", "X": 1}, { "VarName": "y[783,2]", "X": 1}, { "VarName": "y[784,2]", "X": 1}, { "VarName": "y[785,2]", "X": 1}, { "VarName": "y[786,2]", "X": 1}, { "VarName": "y[787,2]", "X": 1}, { "VarName": "y[788,2]", "X": 1}, { "VarName": "y[789,2]", "X": 1}, { "VarName": "y[790,2]", "X": 1}, { "VarName": "y[791,8]", "X": 1}, { "VarName": "y[792,8]", "X": 1}, { "VarName": "y[793,8]", "X": 1}, { "VarName": "y[794,8]", "X": 1}, { "VarName": "y[795,8]", "X": 1}, { "VarName": "y[796,8]", "X": 1}, { "VarName": "y[797,8]", "X": 1}, { "VarName": "y[798,8]", "X": 1}, { "VarName": "y[799,6]", "X": 1}, { "VarName": "y[800,6]", "X": 1}, { "VarName": "y[801,6]", "X": 1}, { "VarName": "y[802,6]", "X": 1}, { "VarName": "y[803,6]", "X": 1}, { "VarName": "y[804,6]", "X": 1}, { "VarName": "y[805,8]", "X": 1}, { "VarName": "y[806,8]", "X": 1}, { "VarName": "y[807,8]", "X": 1}, { "VarName": "y[808,8]", "X": 1}, { "VarName": "y[809,8]", "X": 1}, { "VarName": "y[810,8]", "X": 1}, { "VarName": "y[811,7]", "X": 1}, { "VarName": "y[812,7]", "X": 1}, { "VarName": "y[813,7]", "X": 1}, { "VarName": "y[814,7]", "X": 1}, { "VarName": "y[815,7]", "X": 1}, { "VarName": "y[816,7]", "X": 1}, { "VarName": "y[817,7]", "X": 1}, { "VarName": "y[818,7]", "X": 1}, { "VarName": "y[819,7]", "X": 1}, { "VarName": "y[820,8]", "X": 1}, { "VarName": "y[821,8]", "X": 1}, { "VarName": "y[822,8]", "X": 1}, { "VarName": "y[823,8]", "X": 1}, { "VarName": "y[824,8]", "X": 1}, { "VarName": "y[825,1]", "X": 1}, { "VarName": "y[826,1]", "X": 1}, { "VarName": "y[827,1]", "X": 1}, { "VarName": "y[828,1]", "X": 1}, { "VarName": "y[829,1]", "X": 1}, { "VarName": "y[830,1]", "X": 1}, { "VarName": "y[831,1]", "X": 1}, { "VarName": "y[832,7]", "X": 1}, { "VarName": "y[833,7]", "X": 1}, { "VarName": "y[834,7]", "X": 1}, { "VarName": "y[835,7]", "X": 1}, { "VarName": "y[836,7]", "X": 1}, { "VarName": "y[837,7]", "X": 1}, { "VarName": "y[838,9]", "X": 1}, { "VarName": "y[839,9]", "X": 1}, { "VarName": "y[840,9]", "X": 1}, { "VarName": "y[841,9]", "X": 1}, { "VarName": "y[842,9]", "X": 1}, { "VarName": "y[843,9]", "X": 1}, { "VarName": "y[844,7]", "X": 1}, { "VarName": "y[845,7]", "X": 1}, { "VarName": "y[846,7]", "X": 1}, { "VarName": "y[847,7]", "X": 1}, { "VarName": "y[848,7]", "X": 1}, { "VarName": "y[849,7]", "X": 1}, { "VarName": "y[850,4]", "X": 1}, { "VarName": "y[851,4]", "X": 1}, { "VarName": "y[852,4]", "X": 1}, { "VarName": "y[853,4]", "X": 1}, { "VarName": "y[854,4]", "X": 1}, { "VarName": "y[855,8]", "X": 1}, { "VarName": "y[856,8]", "X": 1}, { "VarName": "y[857,8]", "X": 1}, { "VarName": "y[858,8]", "X": 1}, { "VarName": "y[859,8]", "X": 1}, { "VarName": "y[860,8]", "X": 1}, { "VarName": "y[861,8]", "X": 1}, { "VarName": "y[862,8]", "X": 1}, { "VarName": "y[863,8]", "X": 1}, { "VarName": "y[864,8]", "X": 1}, { "VarName": "y[865,5]", "X": 1}, { "VarName": "y[866,5]", "X": 1}, { "VarName": "y[867,5]", "X": 1}, { "VarName": "y[868,5]", "X": 1}, { "VarName": "y[869,5]", "X": 1}, { "VarName": "y[870,5]", "X": 1}, { "VarName": "y[871,8]", "X": 1}, { "VarName": "y[872,8]", "X": 1}, { "VarName": "y[873,8]", "X": 1}, { "VarName": "y[874,8]", "X": 1}, { "VarName": "y[875,8]", "X": 1}, { "VarName": "y[876,8]", "X": 1}, { "VarName": "y[877,9]", "X": 1}, { "VarName": "y[878,9]", "X": 1}, { "VarName": "y[879,9]", "X": 1}, { "VarName": "y[880,9]", "X": 1}, { "VarName": "y[881,9]", "X": 1}, { "VarName": "y[882,6]", "X": 1}, { "VarName": "y[883,6]", "X": 1}, { "VarName": "y[884,6]", "X": 1}, { "VarName": "y[885,6]", "X": 1}, { "VarName": "y[886,6]", "X": 1}, { "VarName": "y[887,6]", "X": 1}, { "VarName": "y[888,7]", "X": 1}, { "VarName": "y[889,7]", "X": 1}, { "VarName": "y[890,7]", "X": 1}, { "VarName": "y[891,7]", "X": 1}, { "VarName": "y[892,7]", "X": 1}, { "VarName": "y[893,7]", "X": 1}, { "VarName": "y[894,9]", "X": 1}, { "VarName": "y[895,9]", "X": 1}, { "VarName": "y[896,9]", "X": 1}, { "VarName": "y[897,9]", "X": 1}, { "VarName": "y[898,9]", "X": 1}, { "VarName": "y[899,9]", "X": 1}, { "VarName": "y[900,9]", "X": 1}, { "VarName": "y[901,3]", "X": 1}, { "VarName": "y[902,3]", "X": 1}, { "VarName": "y[903,3]", "X": 1}, { "VarName": "y[904,3]", "X": 1}, { "VarName": "y[905,3]", "X": 1}, { "VarName": "y[906,3]", "X": 1}, { "VarName": "y[907,3]", "X": 1}, { "VarName": "y[908,9]", "X": 1}, { "VarName": "y[909,9]", "X": 1}, { "VarName": "y[910,9]", "X": 1}, { "VarName": "y[911,9]", "X": 1}, { "VarName": "y[912,9]", "X": 1}, { "VarName": "y[913,9]", "X": 1}, { "VarName": "y[914,5]", "X": 1}, { "VarName": "y[915,5]", "X": 1}, { "VarName": "y[916,5]", "X": 1}, { "VarName": "y[917,5]", "X": 1}, { "VarName": "y[918,5]", "X": 1}, { "VarName": "y[919,5]", "X": 1}, { "VarName": "y[920,5]", "X": 1}, { "VarName": "y[921,5]", "X": 1}, { "VarName": "y[922,5]", "X": 1}, { "VarName": "y[923,5]", "X": 1}, { "VarName": "y[924,8]", "X": 1}, { "VarName": "y[925,8]", "X": 1}, { "VarName": "y[926,8]", "X": 1}, { "VarName": "y[927,8]", "X": 1}, { "VarName": "y[928,8]", "X": 1}, { "VarName": "y[929,8]", "X": 1}, { "VarName": "y[930,8]", "X": 1}, { "VarName": "y[931,8]", "X": 1}, { "VarName": "y[932,5]", "X": 1}, { "VarName": "y[933,5]", "X": 1}, { "VarName": "y[934,5]", "X": 1}, { "VarName": "y[935,5]", "X": 1}, { "VarName": "y[936,5]", "X": 1}, { "VarName": "y[937,5]", "X": 1}, { "VarName": "y[938,5]", "X": 1}, { "VarName": "y[939,9]", "X": 1}, { "VarName": "y[940,9]", "X": 1}, { "VarName": "y[941,9]", "X": 1}, { "VarName": "y[942,9]", "X": 1}, { "VarName": "y[943,9]", "X": 1}, { "VarName": "y[944,9]", "X": 1}, { "VarName": "y[945,9]", "X": 1}, { "VarName": "y[946,9]", "X": 1}, { "VarName": "y[947,9]", "X": 1}, { "VarName": "y[948,9]", "X": 1}, { "VarName": "y[949,7]", "X": 1}, { "VarName": "y[950,7]", "X": 1}, { "VarName": "y[951,7]", "X": 1}, { "VarName": "y[952,7]", "X": 1}, { "VarName": "y[953,7]", "X": 1}, { "VarName": "y[954,7]", "X": 1}, { "VarName": "y[955,4]", "X": 1}, { "VarName": "y[956,4]", "X": 1}, { "VarName": "y[957,4]", "X": 1}, { "VarName": "y[958,4]", "X": 1}, { "VarName": "y[959,4]", "X": 1}, { "VarName": "y[960,4]", "X": 1}, { "VarName": "y[961,4]", "X": 1}, { "VarName": "y[962,4]", "X": 1}, { "VarName": "y[963,4]", "X": 1}, { "VarName": "y[964,4]", "X": 1}, { "VarName": "y[965,0]", "X": 1}, { "VarName": "y[966,0]", "X": 1}, { "VarName": "y[967,0]", "X": 1}, { "VarName": "y[968,0]", "X": 1}, { "VarName": "y[969,0]", "X": 1}, { "VarName": "y[970,0]", "X": 1}, { "VarName": "y[971,0]", "X": 1}, { "VarName": "y[972,0]", "X": 1}, { "VarName": "y[973,8]", "X": 1}, { "VarName": "y[974,8]", "X": 1}, { "VarName": "y[975,8]", "X": 1}, { "VarName": "y[976,8]", "X": 1}, { "VarName": "y[977,8]", "X": 1}, { "VarName": "y[978,8]", "X": 1}, { "VarName": "y[979,7]", "X": 1}, { "VarName": "y[980,7]", "X": 1}, { "VarName": "y[981,7]", "X": 1}, { "VarName": "y[982,7]", "X": 1}, { "VarName": "y[983,7]", "X": 1}, { "VarName": "y[984,7]", "X": 1}, { "VarName": "y[985,7]", "X": 1}, { "VarName": "y[986,7]", "X": 1}, { "VarName": "y[987,2]", "X": 1}, { "VarName": "y[988,2]", "X": 1}, { "VarName": "y[989,2]", "X": 1}, { "VarName": "y[990,2]", "X": 1}, { "VarName": "y[991,2]", "X": 1}, { "VarName": "y[992,2]", "X": 1}, { "VarName": "y[993,2]", "X": 1}, { "VarName": "y[994,2]", "X": 1}, { "VarName": "y[995,2]", "X": 1}, { "VarName": "y[996,2]", "X": 1}, { "VarName": "y[997,1]", "X": 1}, { "VarName": "y[998,1]", "X": 1}, { "VarName": "y[999,1]", "X": 1}, { "VarName": "y[1000,1]", "X": 1}, { "VarName": "y[1001,1]", "X": 1}, { "VarName": "y[1002,1]", "X": 1}, { "VarName": "y[1003,1]", "X": 1}, { "VarName": "y[1004,8]", "X": 1}, { "VarName": "y[1005,8]", "X": 1}, { "VarName": "y[1006,8]", "X": 1}, { "VarName": "y[1007,8]", "X": 1}, { "VarName": "y[1008,8]", "X": 1}, { "VarName": "y[1009,8]", "X": 1}, { "VarName": "y[1010,8]", "X": 1}, { "VarName": "y[1011,3]", "X": 1}, { "VarName": "y[1012,3]", "X": 1}, { "VarName": "y[1013,3]", "X": 1}, { "VarName": "y[1014,3]", "X": 1}, { "VarName": "y[1015,3]", "X": 1}, { "VarName": "y[1016,3]", "X": 1}, { "VarName": "y[1017,3]", "X": 1}, { "VarName": "y[1018,3]", "X": 1}, { "VarName": "y[1019,7]", "X": 1}, { "VarName": "y[1020,7]", "X": 1}, { "VarName": "y[1021,7]", "X": 1}, { "VarName": "y[1022,7]", "X": 1}, { "VarName": "y[1023,7]", "X": 1}, { "VarName": "y[1024,7]", "X": 1}, { "VarName": "y[1025,8]", "X": 1}, { "VarName": "y[1026,8]", "X": 1}, { "VarName": "y[1027,8]", "X": 1}, { "VarName": "y[1028,8]", "X": 1}, { "VarName": "y[1029,8]", "X": 1}, { "VarName": "y[1030,8]", "X": 1}, { "VarName": "y[1031,8]", "X": 1}, { "VarName": "y[1032,8]", "X": 1}, { "VarName": "y[1033,8]", "X": 1}, { "VarName": "y[1034,9]", "X": 1}, { "VarName": "y[1035,9]", "X": 1}, { "VarName": "y[1036,9]", "X": 1}, { "VarName": "y[1037,9]", "X": 1}, { "VarName": "y[1038,9]", "X": 1}, { "VarName": "y[1039,9]", "X": 1}, { "VarName": "y[1040,9]", "X": 1}, { "VarName": "y[1041,9]", "X": 1}, { "VarName": "y[1042,9]", "X": 1}, { "VarName": "y[1043,3]", "X": 1}, { "VarName": "y[1044,3]", "X": 1}, { "VarName": "y[1045,3]", "X": 1}, { "VarName": "y[1046,3]", "X": 1}, { "VarName": "y[1047,3]", "X": 1}, { "VarName": "y[1048,3]", "X": 1}, { "VarName": "y[1049,3]", "X": 1}, { "VarName": "y[1050,3]", "X": 1}, { "VarName": "y[1051,5]", "X": 1}, { "VarName": "y[1052,5]", "X": 1}, { "VarName": "y[1053,5]", "X": 1}, { "VarName": "y[1054,5]", "X": 1}, { "VarName": "y[1055,5]", "X": 1}, { "VarName": "y[1056,5]", "X": 1}, { "VarName": "y[1057,5]", "X": 1}, { "VarName": "y[1058,5]", "X": 1}, { "VarName": "y[1059,5]", "X": 1}, { "VarName": "y[1060,5]", "X": 1}, { "VarName": "y[1061,9]", "X": 1}, { "VarName": "y[1062,9]", "X": 1}, { "VarName": "y[1063,9]", "X": 1}, { "VarName": "y[1064,9]", "X": 1}, { "VarName": "y[1065,9]", "X": 1}, { "VarName": "y[1066,9]", "X": 1}, { "VarName": "y[1067,9]", "X": 1}, { "VarName": "y[1068,9]", "X": 1}, { "VarName": "y[1069,9]", "X": 1}, { "VarName": "y[1070,5]", "X": 1}, { "VarName": "y[1071,5]", "X": 1}, { "VarName": "y[1072,5]", "X": 1}, { "VarName": "y[1073,5]", "X": 1}, { "VarName": "y[1074,5]", "X": 1}, { "VarName": "y[1075,5]", "X": 1}, { "VarName": "y[1076,5]", "X": 1}, { "VarName": "y[1077,5]", "X": 1}, { "VarName": "y[1078,6]", "X": 1}, { "VarName": "y[1079,6]", "X": 1}, { "VarName": "y[1080,6]", "X": 1}, { "VarName": "y[1081,6]", "X": 1}, { "VarName": "y[1082,6]", "X": 1}, { "VarName": "y[1083,3]", "X": 1}, { "VarName": "y[1084,3]", "X": 1}, { "VarName": "y[1085,3]", "X": 1}, { "VarName": "y[1086,3]", "X": 1}, { "VarName": "y[1087,3]", "X": 1}, { "VarName": "y[1088,3]", "X": 1}, { "VarName": "y[1089,3]", "X": 1}, { "VarName": "y[1090,6]", "X": 1}, { "VarName": "y[1091,6]", "X": 1}, { "VarName": "y[1092,6]", "X": 1}, { "VarName": "y[1093,6]", "X": 1}, { "VarName": "y[1094,6]", "X": 1}, { "VarName": "y[1095,6]", "X": 1}, { "VarName": "y[1096,1]", "X": 1}, { "VarName": "y[1097,1]", "X": 1}, { "VarName": "y[1098,1]", "X": 1}, { "VarName": "y[1099,1]", "X": 1}, { "VarName": "y[1100,1]", "X": 1}, { "VarName": "y[1101,7]", "X": 1}, { "VarName": "y[1102,7]", "X": 1}, { "VarName": "y[1103,7]", "X": 1}, { "VarName": "y[1104,7]", "X": 1}, { "VarName": "y[1105,7]", "X": 1}, { "VarName": "y[1106,7]", "X": 1}, { "VarName": "y[1107,7]", "X": 1}, { "VarName": "y[1108,7]", "X": 1}, { "VarName": "y[1109,8]", "X": 1}, { "VarName": "y[1110,8]", "X": 1}, { "VarName": "y[1111,8]", "X": 1}, { "VarName": "y[1112,8]", "X": 1}, { "VarName": "y[1113,8]", "X": 1}, { "VarName": "y[1114,8]", "X": 1}, { "VarName": "y[1115,8]", "X": 1}, { "VarName": "y[1116,7]", "X": 1}, { "VarName": "y[1117,7]", "X": 1}, { "VarName": "y[1118,7]", "X": 1}, { "VarName": "y[1119,7]", "X": 1}, { "VarName": "y[1120,7]", "X": 1}, { "VarName": "y[1121,7]", "X": 1}, { "VarName": "y[1122,7]", "X": 1}, { "VarName": "y[1123,7]", "X": 1}, { "VarName": "y[1124,7]", "X": 1}, { "VarName": "y[1125,7]", "X": 1}, { "VarName": "y[1126,7]", "X": 1}, { "VarName": "y[1127,7]", "X": 1}, { "VarName": "y[1128,7]", "X": 1}, { "VarName": "y[1129,7]", "X": 1}, { "VarName": "y[1130,7]", "X": 1}, { "VarName": "y[1131,7]", "X": 1}, { "VarName": "y[1132,4]", "X": 1}, { "VarName": "y[1133,4]", "X": 1}, { "VarName": "y[1134,4]", "X": 1}, { "VarName": "y[1135,4]", "X": 1}, { "VarName": "y[1136,4]", "X": 1}, { "VarName": "y[1137,4]", "X": 1}, { "VarName": "y[1138,4]", "X": 1}, { "VarName": "y[1139,4]", "X": 1}, { "VarName": "y[1140,4]", "X": 1}, { "VarName": "y[1141,6]", "X": 1}, { "VarName": "y[1142,6]", "X": 1}, { "VarName": "y[1143,6]", "X": 1}, { "VarName": "y[1144,6]", "X": 1}, { "VarName": "y[1145,6]", "X": 1}, { "VarName": "y[1146,6]", "X": 1}, { "VarName": "y[1147,6]", "X": 1}, { "VarName": "y[1148,5]", "X": 1}, { "VarName": "y[1149,5]", "X": 1}, { "VarName": "y[1150,5]", "X": 1}, { "VarName": "y[1151,5]", "X": 1}, { "VarName": "y[1152,5]", "X": 1}, { "VarName": "y[1153,5]", "X": 1}, { "VarName": "y[1154,5]", "X": 1}, { "VarName": "y[1155,5]", "X": 1}, { "VarName": "y[1156,5]", "X": 1}, { "VarName": "y[1157,8]", "X": 1}, { "VarName": "y[1158,8]", "X": 1}, { "VarName": "y[1159,8]", "X": 1}, { "VarName": "y[1160,8]", "X": 1}, { "VarName": "y[1161,8]", "X": 1}, { "VarName": "y[1162,8]", "X": 1}, { "VarName": "y[1163,8]", "X": 1}, { "VarName": "y[1164,8]", "X": 1}, { "VarName": "y[1165,8]", "X": 1}, { "VarName": "y[1166,8]", "X": 1}, { "VarName": "y[1167,9]", "X": 1}, { "VarName": "y[1168,9]", "X": 1}, { "VarName": "y[1169,9]", "X": 1}, { "VarName": "y[1170,9]", "X": 1}, { "VarName": "y[1171,9]", "X": 1}, { "VarName": "y[1172,9]", "X": 1}, { "VarName": "y[1173,9]", "X": 1}, { "VarName": "y[1174,9]", "X": 1}, { "VarName": "y[1175,9]", "X": 1}, { "VarName": "y[1176,9]", "X": 1}, { "VarName": "y[1177,3]", "X": 1}, { "VarName": "y[1178,3]", "X": 1}, { "VarName": "y[1179,3]", "X": 1}, { "VarName": "y[1180,3]", "X": 1}, { "VarName": "y[1181,3]", "X": 1}, { "VarName": "y[1182,3]", "X": 1}, { "VarName": "y[1183,3]", "X": 1}, { "VarName": "y[1184,8]", "X": 1}, { "VarName": "y[1185,8]", "X": 1}, { "VarName": "y[1186,8]", "X": 1}, { "VarName": "y[1187,8]", "X": 1}, { "VarName": "y[1188,8]", "X": 1}, { "VarName": "y[1189,7]", "X": 1}, { "VarName": "y[1190,7]", "X": 1}, { "VarName": "y[1191,7]", "X": 1}, { "VarName": "y[1192,7]", "X": 1}, { "VarName": "y[1193,7]", "X": 1}, { "VarName": "y[1194,7]", "X": 1}, { "VarName": "y[1195,4]", "X": 1}, { "VarName": "y[1196,4]", "X": 1}, { "VarName": "y[1197,4]", "X": 1}, { "VarName": "y[1198,4]", "X": 1}, { "VarName": "y[1199,4]", "X": 1}, { "VarName": "y[1200,4]", "X": 1}, { "VarName": "y[1201,4]", "X": 1}, { "VarName": "y[1202,9]", "X": 1}, { "VarName": "y[1203,9]", "X": 1}, { "VarName": "y[1204,9]", "X": 1}, { "VarName": "y[1205,9]", "X": 1}, { "VarName": "y[1206,9]", "X": 1}, { "VarName": "y[1207,9]", "X": 1}, { "VarName": "y[1208,9]", "X": 1}, { "VarName": "y[1209,9]", "X": 1}, { "VarName": "y[1210,8]", "X": 1}, { "VarName": "y[1211,8]", "X": 1}, { "VarName": "y[1212,8]", "X": 1}, { "VarName": "y[1213,8]", "X": 1}, { "VarName": "y[1214,8]", "X": 1}, { "VarName": "y[1215,8]", "X": 1}, { "VarName": "y[1216,8]", "X": 1}, { "VarName": "y[1217,5]", "X": 1}, { "VarName": "y[1218,5]", "X": 1}, { "VarName": "y[1219,5]", "X": 1}, { "VarName": "y[1220,5]", "X": 1}, { "VarName": "y[1221,5]", "X": 1}, { "VarName": "y[1222,5]", "X": 1}, { "VarName": "y[1223,5]", "X": 1}, { "VarName": "y[1224,5]", "X": 1}, { "VarName": "y[1225,5]", "X": 1}, { "VarName": "y[1226,0]", "X": 1}, { "VarName": "y[1227,0]", "X": 1}, { "VarName": "y[1228,0]", "X": 1}, { "VarName": "y[1229,0]", "X": 1}, { "VarName": "y[1230,0]", "X": 1}, { "VarName": "y[1231,0]", "X": 1}, { "VarName": "y[1232,6]", "X": 1}, { "VarName": "y[1233,6]", "X": 1}, { "VarName": "y[1234,6]", "X": 1}, { "VarName": "y[1235,6]", "X": 1}, { "VarName": "y[1236,6]", "X": 1}, { "VarName": "y[1237,6]", "X": 1}, { "VarName": "y[1238,6]", "X": 1}, { "VarName": "y[1239,6]", "X": 1}, { "VarName": "y[1240,9]", "X": 1}, { "VarName": "y[1241,9]", "X": 1}, { "VarName": "y[1242,9]", "X": 1}, { "VarName": "y[1243,9]", "X": 1}, { "VarName": "y[1244,9]", "X": 1}, { "VarName": "y[1245,9]", "X": 1}, { "VarName": "y[1246,9]", "X": 1}, { "VarName": "y[1247,9]", "X": 1}, { "VarName": "y[1248,9]", "X": 1}, { "VarName": "y[1249,9]", "X": 1}, { "VarName": "y[1250,9]", "X": 1}, { "VarName": "y[1251,9]", "X": 1}, { "VarName": "y[1252,9]", "X": 1}, { "VarName": "y[1253,9]", "X": 1}, { "VarName": "y[1254,4]", "X": 1}, { "VarName": "y[1255,4]", "X": 1}, { "VarName": "y[1256,4]", "X": 1}, { "VarName": "y[1257,4]", "X": 1}, { "VarName": "y[1258,4]", "X": 1}, { "VarName": "y[1259,7]", "X": 1}, { "VarName": "y[1260,7]", "X": 1}, { "VarName": "y[1261,7]", "X": 1}, { "VarName": "y[1262,7]", "X": 1}, { "VarName": "y[1263,7]", "X": 1}, { "VarName": "y[1264,7]", "X": 1}, { "VarName": "y[1265,5]", "X": 1}, { "VarName": "y[1266,5]", "X": 1}, { "VarName": "y[1267,5]", "X": 1}, { "VarName": "y[1268,5]", "X": 1}, { "VarName": "y[1269,5]", "X": 1}, { "VarName": "y[1270,5]", "X": 1}, { "VarName": "y[1271,5]", "X": 1}, { "VarName": "y[1272,5]", "X": 1}, { "VarName": "y[1273,9]", "X": 1}, { "VarName": "y[1274,9]", "X": 1}, { "VarName": "y[1275,9]", "X": 1}, { "VarName": "y[1276,9]", "X": 1}, { "VarName": "y[1277,9]", "X": 1}, { "VarName": "y[1278,6]", "X": 1}, { "VarName": "y[1279,6]", "X": 1}, { "VarName": "y[1280,6]", "X": 1}, { "VarName": "y[1281,6]", "X": 1}, { "VarName": "y[1282,6]", "X": 1}, { "VarName": "y[1283,6]", "X": 1}, { "VarName": "y[1284,5]", "X": 1}, { "VarName": "y[1285,5]", "X": 1}, { "VarName": "y[1286,5]", "X": 1}, { "VarName": "y[1287,5]", "X": 1}, { "VarName": "y[1288,5]", "X": 1}, { "VarName": "y[1289,5]", "X": 1}, { "VarName": "y[1290,5]", "X": 1}, { "VarName": "y[1291,5]", "X": 1}, { "VarName": "y[1292,5]", "X": 1}, { "VarName": "y[1293,1]", "X": 1}, { "VarName": "y[1294,1]", "X": 1}, { "VarName": "y[1295,1]", "X": 1}, { "VarName": "y[1296,1]", "X": 1}, { "VarName": "y[1297,1]", "X": 1}, { "VarName": "y[1298,1]", "X": 1}, { "VarName": "y[1299,1]", "X": 1}, { "VarName": "y[1300,1]", "X": 1}, { "VarName": "y[1301,5]", "X": 1}, { "VarName": "y[1302,5]", "X": 1}, { "VarName": "y[1303,5]", "X": 1}, { "VarName": "y[1304,5]", "X": 1}, { "VarName": "y[1305,5]", "X": 1}, { "VarName": "y[1306,5]", "X": 1}, { "VarName": "y[1307,5]", "X": 1}, { "VarName": "y[1308,5]", "X": 1}, { "VarName": "y[1309,2]", "X": 1}, { "VarName": "y[1310,2]", "X": 1}, { "VarName": "y[1311,2]", "X": 1}, { "VarName": "y[1312,2]", "X": 1}, { "VarName": "y[1313,2]", "X": 1}, { "VarName": "y[1314,2]", "X": 1}, { "VarName": "y[1315,9]", "X": 1}, { "VarName": "y[1316,9]", "X": 1}, { "VarName": "y[1317,9]", "X": 1}, { "VarName": "y[1318,9]", "X": 1}, { "VarName": "y[1319,9]", "X": 1}, { "VarName": "y[1320,9]", "X": 1}, { "VarName": "y[1321,9]", "X": 1}, { "VarName": "y[1322,9]", "X": 1}, { "VarName": "y[1323,9]", "X": 1}, { "VarName": "y[1324,9]", "X": 1}, { "VarName": "y[1325,5]", "X": 1}, { "VarName": "y[1326,5]", "X": 1}, { "VarName": "y[1327,5]", "X": 1}, { "VarName": "y[1328,5]", "X": 1}, { "VarName": "y[1329,5]", "X": 1}, { "VarName": "y[1330,5]", "X": 1}, { "VarName": "y[1331,5]", "X": 1}, { "VarName": "y[1332,5]", "X": 1}, { "VarName": "y[1333,5]", "X": 1}, { "VarName": "y[1334,5]", "X": 1}, { "VarName": "y[1335,7]", "X": 1}, { "VarName": "y[1336,7]", "X": 1}, { "VarName": "y[1337,7]", "X": 1}, { "VarName": "y[1338,7]", "X": 1}, { "VarName": "y[1339,7]", "X": 1}, { "VarName": "y[1340,8]", "X": 1}, { "VarName": "y[1341,8]", "X": 1}, { "VarName": "y[1342,8]", "X": 1}, { "VarName": "y[1343,8]", "X": 1}, { "VarName": "y[1344,8]", "X": 1}, { "VarName": "y[1345,8]", "X": 1}, { "VarName": "y[1346,8]", "X": 1}, { "VarName": "y[1347,8]", "X": 1}, { "VarName": "y[1348,8]", "X": 1}, { "VarName": "y[1349,8]", "X": 1}, { "VarName": "y[1350,8]", "X": 1}, { "VarName": "y[1351,8]", "X": 1}, { "VarName": "y[1352,8]", "X": 1}, { "VarName": "y[1353,8]", "X": 1}, { "VarName": "y[1354,5]", "X": 1}, { "VarName": "y[1355,5]", "X": 1}, { "VarName": "y[1356,5]", "X": 1}, { "VarName": "y[1357,5]", "X": 1}, { "VarName": "y[1358,5]", "X": 1}, { "VarName": "y[1359,5]", "X": 1}, { "VarName": "y[1360,5]", "X": 1}, { "VarName": "y[1361,5]", "X": 1}, { "VarName": "y[1362,5]", "X": 1}, { "VarName": "y[1363,5]", "X": 1}, { "VarName": "y[1364,6]", "X": 1}, { "VarName": "y[1365,6]", "X": 1}, { "VarName": "y[1366,6]", "X": 1}, { "VarName": "y[1367,6]", "X": 1}, { "VarName": "y[1368,6]", "X": 1}, { "VarName": "y[1369,6]", "X": 1}, { "VarName": "y[1370,6]", "X": 1}, { "VarName": "y[1371,7]", "X": 1}, { "VarName": "y[1372,7]", "X": 1}, { "VarName": "y[1373,7]", "X": 1}, { "VarName": "y[1374,7]", "X": 1}, { "VarName": "y[1375,7]", "X": 1}, { "VarName": "y[1376,7]", "X": 1}, { "VarName": "y[1377,7]", "X": 1}, { "VarName": "y[1378,7]", "X": 1}, { "VarName": "y[1379,7]", "X": 1}, { "VarName": "y[1380,3]", "X": 1}, { "VarName": "y[1381,3]", "X": 1}, { "VarName": "y[1382,3]", "X": 1}, { "VarName": "y[1383,3]", "X": 1}, { "VarName": "y[1384,3]", "X": 1}, { "VarName": "y[1385,3]", "X": 1}, { "VarName": "y[1386,3]", "X": 1}, { "VarName": "y[1387,3]", "X": 1}, { "VarName": "y[1388,7]", "X": 1}, { "VarName": "y[1389,7]", "X": 1}, { "VarName": "y[1390,7]", "X": 1}, { "VarName": "y[1391,7]", "X": 1}, { "VarName": "y[1392,7]", "X": 1}, { "VarName": "y[1393,7]", "X": 1}, { "VarName": "y[1394,7]", "X": 1}, { "VarName": "y[1395,7]", "X": 1}, { "VarName": "y[1396,7]", "X": 1}, { "VarName": "y[1397,5]", "X": 1}, { "VarName": "y[1398,5]", "X": 1}, { "VarName": "y[1399,5]", "X": 1}, { "VarName": "y[1400,5]", "X": 1}, { "VarName": "y[1401,5]", "X": 1}, { "VarName": "y[1402,5]", "X": 1}, { "VarName": "y[1403,1]", "X": 1}, { "VarName": "y[1404,1]", "X": 1}, { "VarName": "y[1405,1]", "X": 1}, { "VarName": "y[1406,1]", "X": 1}, { "VarName": "y[1407,1]", "X": 1}, { "VarName": "y[1408,1]", "X": 1}, { "VarName": "y[1409,1]", "X": 1}, { "VarName": "y[1410,1]", "X": 1}, { "VarName": "y[1411,1]", "X": 1}, { "VarName": "y[1412,1]", "X": 1}, { "VarName": "y[1413,5]", "X": 1}, { "VarName": "y[1414,5]", "X": 1}, { "VarName": "y[1415,5]", "X": 1}, { "VarName": "y[1416,5]", "X": 1}, { "VarName": "y[1417,5]", "X": 1}, { "VarName": "y[1418,5]", "X": 1}, { "VarName": "y[1419,6]", "X": 1}, { "VarName": "y[1420,6]", "X": 1}, { "VarName": "y[1421,6]", "X": 1}, { "VarName": "y[1422,6]", "X": 1}, { "VarName": "y[1423,6]", "X": 1}, { "VarName": "y[1424,6]", "X": 1}, { "VarName": "y[1425,6]", "X": 1}, { "VarName": "y[1426,6]", "X": 1}, { "VarName": "y[1427,6]", "X": 1}, { "VarName": "y[1428,6]", "X": 1}, { "VarName": "y[1429,7]", "X": 1}, { "VarName": "y[1430,7]", "X": 1}, { "VarName": "y[1431,7]", "X": 1}, { "VarName": "y[1432,7]", "X": 1}, { "VarName": "y[1433,7]", "X": 1}, { "VarName": "y[1434,3]", "X": 1}, { "VarName": "y[1435,3]", "X": 1}, { "VarName": "y[1436,3]", "X": 1}, { "VarName": "y[1437,3]", "X": 1}, { "VarName": "y[1438,3]", "X": 1}, { "VarName": "y[1439,5]", "X": 1}, { "VarName": "y[1440,5]", "X": 1}, { "VarName": "y[1441,5]", "X": 1}, { "VarName": "y[1442,5]", "X": 1}, { "VarName": "y[1443,5]", "X": 1}, { "VarName": "y[1444,5]", "X": 1}, { "VarName": "y[1445,5]", "X": 1}, { "VarName": "y[1446,5]", "X": 1}, { "VarName": "y[1447,5]", "X": 1}, { "VarName": "y[1448,1]", "X": 1}, { "VarName": "y[1449,1]", "X": 1}, { "VarName": "y[1450,1]", "X": 1}, { "VarName": "y[1451,1]", "X": 1}, { "VarName": "y[1452,1]", "X": 1}, { "VarName": "y[1453,1]", "X": 1}, { "VarName": "y[1454,1]", "X": 1}, { "VarName": "y[1455,0]", "X": 1}, { "VarName": "y[1456,0]", "X": 1}, { "VarName": "y[1457,0]", "X": 1}, { "VarName": "y[1458,0]", "X": 1}, { "VarName": "y[1459,0]", "X": 1}, { "VarName": "y[1460,0]", "X": 1}, { "VarName": "y[1461,0]", "X": 1}, { "VarName": "y[1462,0]", "X": 1}, { "VarName": "y[1463,0]", "X": 1}, { "VarName": "y[1464,0]", "X": 1}, { "VarName": "y[1465,7]", "X": 1}, { "VarName": "y[1466,7]", "X": 1}, { "VarName": "y[1467,7]", "X": 1}, { "VarName": "y[1468,7]", "X": 1}, { "VarName": "y[1469,7]", "X": 1}, { "VarName": "y[1470,7]", "X": 1}, { "VarName": "y[1471,7]", "X": 1}, { "VarName": "y[1472,8]", "X": 1}, { "VarName": "y[1473,8]", "X": 1}, { "VarName": "y[1474,8]", "X": 1}, { "VarName": "y[1475,8]", "X": 1}, { "VarName": "y[1476,8]", "X": 1}, { "VarName": "y[1477,8]", "X": 1}, { "VarName": "y[1478,8]", "X": 1}, { "VarName": "y[1479,8]", "X": 1}, { "VarName": "y[1480,7]", "X": 1}, { "VarName": "y[1481,7]", "X": 1}, { "VarName": "y[1482,7]", "X": 1}, { "VarName": "y[1483,7]", "X": 1}, { "VarName": "y[1484,7]", "X": 1}, { "VarName": "y[1485,7]", "X": 1}, { "VarName": "y[1486,7]", "X": 1}, { "VarName": "y[1487,7]", "X": 1}, { "VarName": "y[1488,7]", "X": 1}, { "VarName": "y[1489,7]", "X": 1}, { "VarName": "y[1490,6]", "X": 1}, { "VarName": "y[1491,6]", "X": 1}, { "VarName": "y[1492,6]", "X": 1}, { "VarName": "y[1493,6]", "X": 1}, { "VarName": "y[1494,6]", "X": 1}, { "VarName": "y[1495,6]", "X": 1}, { "VarName": "y[1496,1]", "X": 1}, { "VarName": "y[1497,1]", "X": 1}, { "VarName": "y[1498,1]", "X": 1}, { "VarName": "y[1499,1]", "X": 1}, { "VarName": "y[1500,1]", "X": 1}, { "VarName": "y[1501,1]", "X": 1}, { "VarName": "y[1502,1]", "X": 1}, { "VarName": "y[1503,1]", "X": 1}, { "VarName": "y[1504,1]", "X": 1}, { "VarName": "y[1505,1]", "X": 1}, { "VarName": "y[1506,0]", "X": 1}, { "VarName": "y[1507,0]", "X": 1}, { "VarName": "y[1508,0]", "X": 1}, { "VarName": "y[1509,0]", "X": 1}, { "VarName": "y[1510,0]", "X": 1}, { "VarName": "y[1511,0]", "X": 1}, { "VarName": "y[1512,0]", "X": 1}, { "VarName": "y[1513,0]", "X": 1}, { "VarName": "y[1514,0]", "X": 1}, { "VarName": "y[1515,0]", "X": 1}, { "VarName": "y[1516,6]", "X": 1}, { "VarName": "y[1517,6]", "X": 1}, { "VarName": "y[1518,6]", "X": 1}, { "VarName": "y[1519,6]", "X": 1}, { "VarName": "y[1520,6]", "X": 1}, { "VarName": "y[1521,6]", "X": 1}, { "VarName": "y[1522,5]", "X": 1}, { "VarName": "y[1523,5]", "X": 1}, { "VarName": "y[1524,5]", "X": 1}, { "VarName": "y[1525,5]", "X": 1}, { "VarName": "y[1526,5]", "X": 1}, { "VarName": "y[1527,5]", "X": 1}, { "VarName": "y[1528,5]", "X": 1}, { "VarName": "y[1529,5]", "X": 1}, { "VarName": "y[1530,3]", "X": 1}, { "VarName": "y[1531,3]", "X": 1}, { "VarName": "y[1532,3]", "X": 1}, { "VarName": "y[1533,3]", "X": 1}, { "VarName": "y[1534,3]", "X": 1}, { "VarName": "y[1535,0]", "X": 1}, { "VarName": "y[1536,0]", "X": 1}, { "VarName": "y[1537,0]", "X": 1}, { "VarName": "y[1538,0]", "X": 1}, { "VarName": "y[1539,0]", "X": 1}, { "VarName": "y[1540,0]", "X": 1}, { "VarName": "y[1541,6]", "X": 1}, { "VarName": "y[1542,6]", "X": 1}, { "VarName": "y[1543,6]", "X": 1}, { "VarName": "y[1544,6]", "X": 1}, { "VarName": "y[1545,6]", "X": 1}, { "VarName": "y[1546,5]", "X": 1}, { "VarName": "y[1547,5]", "X": 1}, { "VarName": "y[1548,5]", "X": 1}, { "VarName": "y[1549,5]", "X": 1}, { "VarName": "y[1550,5]", "X": 1}, { "VarName": "y[1551,5]", "X": 1}, { "VarName": "y[1552,5]", "X": 1}, { "VarName": "y[1553,5]", "X": 1}, { "VarName": "y[1554,5]", "X": 1}, { "VarName": "y[1555,5]", "X": 1}, { "VarName": "y[1556,5]", "X": 1}, { "VarName": "y[1557,5]", "X": 1}, { "VarName": "y[1558,5]", "X": 1}, { "VarName": "y[1559,5]", "X": 1}, { "VarName": "y[1560,5]", "X": 1}, { "VarName": "y[1561,8]", "X": 1}, { "VarName": "y[1562,8]", "X": 1}, { "VarName": "y[1563,8]", "X": 1}, { "VarName": "y[1564,8]", "X": 1}, { "VarName": "y[1565,8]", "X": 1}, { "VarName": "y[1566,9]", "X": 1}, { "VarName": "y[1567,9]", "X": 1}, { "VarName": "y[1568,9]", "X": 1}, { "VarName": "y[1569,9]", "X": 1}, { "VarName": "y[1570,9]", "X": 1}, { "VarName": "y[1571,9]", "X": 1}, { "VarName": "y[1572,8]", "X": 1}, { "VarName": "y[1573,8]", "X": 1}, { "VarName": "y[1574,8]", "X": 1}, { "VarName": "y[1575,8]", "X": 1}, { "VarName": "y[1576,8]", "X": 1}, { "VarName": "y[1577,8]", "X": 1}, { "VarName": "y[1578,4]", "X": 1}, { "VarName": "y[1579,4]", "X": 1}, { "VarName": "y[1580,4]", "X": 1}, { "VarName": "y[1581,4]", "X": 1}, { "VarName": "y[1582,4]", "X": 1}, { "VarName": "y[1583,4]", "X": 1}, { "VarName": "y[1584,9]", "X": 1}, { "VarName": "y[1585,9]", "X": 1}, { "VarName": "y[1586,9]", "X": 1}, { "VarName": "y[1587,9]", "X": 1}, { "VarName": "y[1588,9]", "X": 1}, { "VarName": "y[1589,9]", "X": 1}, { "VarName": "y[1590,9]", "X": 1}, { "VarName": "y[1591,9]", "X": 1}, { "VarName": "y[1592,9]", "X": 1}, { "VarName": "y[1593,5]", "X": 1}, { "VarName": "y[1594,5]", "X": 1}, { "VarName": "y[1595,5]", "X": 1}, { "VarName": "y[1596,5]", "X": 1}, { "VarName": "y[1597,5]", "X": 1}, { "VarName": "y[1598,5]", "X": 1}, { "VarName": "y[1599,5]", "X": 1}, { "VarName": "y[1600,5]", "X": 1}, { "VarName": "y[1601,5]", "X": 1}, { "VarName": "y[1602,5]", "X": 1}, { "VarName": "y[1603,7]", "X": 1}, { "VarName": "y[1604,7]", "X": 1}, { "VarName": "y[1605,7]", "X": 1}, { "VarName": "y[1606,7]", "X": 1}, { "VarName": "y[1607,7]", "X": 1}, { "VarName": "y[1608,7]", "X": 1}, { "VarName": "y[1609,7]", "X": 1}, { "VarName": "y[1610,7]", "X": 1}, { "VarName": "y[1611,5]", "X": 1}, { "VarName": "y[1612,5]", "X": 1}, { "VarName": "y[1613,5]", "X": 1}, { "VarName": "y[1614,5]", "X": 1}, { "VarName": "y[1615,5]", "X": 1}, { "VarName": "y[1616,5]", "X": 1}, { "VarName": "y[1617,5]", "X": 1}, { "VarName": "y[1618,5]", "X": 1}, { "VarName": "y[1619,5]", "X": 1}, { "VarName": "y[1620,5]", "X": 1}, { "VarName": "y[1621,7]", "X": 1}, { "VarName": "y[1622,7]", "X": 1}, { "VarName": "y[1623,7]", "X": 1}, { "VarName": "y[1624,7]", "X": 1}, { "VarName": "y[1625,7]", "X": 1}, { "VarName": "y[1626,7]", "X": 1}, { "VarName": "y[1627,7]", "X": 1}, { "VarName": "z[0,6]", "X": 1}, { "VarName": "z[1,0]", "X": 1}, { "VarName": "z[2,0]", "X": 1}, { "VarName": "z[3,0]", "X": 1}, { "VarName": "z[4,8]", "X": 1}, { "VarName": "z[5,0]", "X": 1}, { "VarName": "z[6,8]", "X": 1}, { "VarName": "z[7,0]", "X": 1}, { "VarName": "z[8,0]", "X": 1}, { "VarName": "z[9,9]", "X": 1}, { "VarName": "z[10,0]", "X": 1}, { "VarName": "z[11,9]", "X": 1}, { "VarName": "z[12,8]", "X": 1}, { "VarName": "z[13,6]", "X": 1}, { "VarName": "z[14,2]", "X": 1}, { "VarName": "z[15,6]", "X": 1}, { "VarName": "z[16,9]", "X": 1}, { "VarName": "z[17,7]", "X": 1}, { "VarName": "z[18,2]", "X": 1}, { "VarName": "z[19,6]", "X": 1}, { "VarName": "z[20,6]", "X": 1}, { "VarName": "z[21,2]", "X": 1}, { "VarName": "z[22,6]", "X": 1}, { "VarName": "z[23,4]", "X": 1}, { "VarName": "z[24,8]", "X": 1}, { "VarName": "z[25,6]", "X": 1}, { "VarName": "z[26,8]", "X": 1}, { "VarName": "z[27,9]", "X": 1}, { "VarName": "z[28,4]", "X": 1}, { "VarName": "z[29,9]", "X": 1}, { "VarName": "z[30,9]", "X": 1}, { "VarName": "z[31,1]", "X": 1}, { "VarName": "z[32,8]", "X": 1}, { "VarName": "z[33,2]", "X": 1}, { "VarName": "z[34,5]", "X": 1}, { "VarName": "z[35,9]", "X": 1}, { "VarName": "z[36,4]", "X": 1}, { "VarName": "z[37,1]", "X": 1}, { "VarName": "z[38,4]", "X": 1}, { "VarName": "z[39,6]", "X": 1}, { "VarName": "z[40,6]", "X": 1}, { "VarName": "z[41,7]", "X": 1}, { "VarName": "z[42,2]", "X": 1}, { "VarName": "z[43,7]", "X": 1}, { "VarName": "z[44,7]", "X": 1}, { "VarName": "z[45,4]", "X": 1}, { "VarName": "z[46,2]", "X": 1}, { "VarName": "z[47,8]", "X": 1}, { "VarName": "z[48,2]", "X": 1}, { "VarName": "z[49,4]", "X": 1}, { "VarName": "z[50,8]", "X": 1}, { "VarName": "z[51,3]", "X": 1}, { "VarName": "z[52,0]", "X": 1}, { "VarName": "z[53,1]", "X": 1}, { "VarName": "z[54,9]", "X": 1}, { "VarName": "z[55,9]", "X": 1}, { "VarName": "z[56,7]", "X": 1}, { "VarName": "z[57,3]", "X": 1}, { "VarName": "z[58,6]", "X": 1}, { "VarName": "z[59,2]", "X": 1}, { "VarName": "z[60,0]", "X": 1}, { "VarName": "z[61,6]", "X": 1}, { "VarName": "z[62,6]", "X": 1}, { "VarName": "z[63,2]", "X": 1}, { "VarName": "z[64,8]", "X": 1}, { "VarName": "z[65,3]", "X": 1}, { "VarName": "z[66,5]", "X": 1}, { "VarName": "z[67,9]", "X": 1}, { "VarName": "z[68,7]", "X": 1}, { "VarName": "z[69,7]", "X": 1}, { "VarName": "z[70,5]", "X": 1}, { "VarName": "z[71,4]", "X": 1}, { "VarName": "z[72,6]", "X": 1}, { "VarName": "z[73,8]", "X": 1}, { "VarName": "z[74,9]", "X": 1}, { "VarName": "z[75,5]", "X": 1}, { "VarName": "z[76,6]", "X": 1}, { "VarName": "z[77,8]", "X": 1}, { "VarName": "z[78,6]", "X": 1}, { "VarName": "z[79,2]", "X": 1}, { "VarName": "z[80,1]", "X": 1}, { "VarName": "z[81,4]", "X": 1}, { "VarName": "z[82,8]", "X": 1}, { "VarName": "z[83,5]", "X": 1}, { "VarName": "z[84,5]", "X": 1}, { "VarName": "z[85,5]", "X": 1}, { "VarName": "z[86,1]", "X": 1}, { "VarName": "z[87,9]", "X": 1}, { "VarName": "z[88,9]", "X": 1}, { "VarName": "z[89,3]", "X": 1}, { "VarName": "z[90,5]", "X": 1}, { "VarName": "z[91,4]", "X": 1}, { "VarName": "z[92,7]", "X": 1}, { "VarName": "z[93,8]", "X": 1}, { "VarName": "z[94,6]", "X": 1}, { "VarName": "z[95,6]", "X": 1}, { "VarName": "z[96,2]", "X": 1}, { "VarName": "z[97,6]", "X": 1}, { "VarName": "z[98,1]", "X": 1}, { "VarName": "z[99,5]", "X": 1}, { "VarName": "z[100,9]", "X": 1}, { "VarName": "z[101,4]", "X": 1}, { "VarName": "z[102,8]", "X": 1}, { "VarName": "z[103,3]", "X": 1}, { "VarName": "z[104,9]", "X": 1}, { "VarName": "z[105,0]", "X": 1}, { "VarName": "z[106,2]", "X": 1}, { "VarName": "z[107,8]", "X": 1}, { "VarName": "z[108,6]", "X": 1}, { "VarName": "z[109,8]", "X": 1}, { "VarName": "z[110,7]", "X": 1}, { "VarName": "z[111,8]", "X": 1}, { "VarName": "z[112,1]", "X": 1}, { "VarName": "z[113,7]", "X": 1}, { "VarName": "z[114,9]", "X": 1}, { "VarName": "z[115,7]", "X": 1}, { "VarName": "z[116,4]", "X": 1}, { "VarName": "z[117,8]", "X": 1}, { "VarName": "z[118,5]", "X": 1}, { "VarName": "z[119,8]", "X": 1}, { "VarName": "z[120,9]", "X": 1}, { "VarName": "z[121,6]", "X": 1}, { "VarName": "z[122,7]", "X": 1}, { "VarName": "z[123,9]", "X": 1}, { "VarName": "z[124,3]", "X": 1}, { "VarName": "z[125,9]", "X": 1}, { "VarName": "z[126,5]", "X": 1}, { "VarName": "z[127,8]", "X": 1}, { "VarName": "z[128,5]", "X": 1}, { "VarName": "z[129,9]", "X": 1}, { "VarName": "z[130,7]", "X": 1}, { "VarName": "z[131,4]", "X": 1}, { "VarName": "z[132,0]", "X": 1}, { "VarName": "z[133,8]", "X": 1}, { "VarName": "z[134,7]", "X": 1}, { "VarName": "z[135,2]", "X": 1}, { "VarName": "z[136,1]", "X": 1}, { "VarName": "z[137,8]", "X": 1}, { "VarName": "z[138,3]", "X": 1}, { "VarName": "z[139,7]", "X": 1}, { "VarName": "z[140,8]", "X": 1}, { "VarName": "z[141,9]", "X": 1}, { "VarName": "z[142,3]", "X": 1}, { "VarName": "z[143,5]", "X": 1}, { "VarName": "z[144,9]", "X": 1}, { "VarName": "z[145,5]", "X": 1}, { "VarName": "z[146,6]", "X": 1}, { "VarName": "z[147,3]", "X": 1}, { "VarName": "z[148,6]", "X": 1}, { "VarName": "z[149,1]", "X": 1}, { "VarName": "z[150,7]", "X": 1}, { "VarName": "z[151,8]", "X": 1}, { "VarName": "z[152,7]", "X": 1}, { "VarName": "z[153,7]", "X": 1}, { "VarName": "z[154,4]", "X": 1}, { "VarName": "z[155,6]", "X": 1}, { "VarName": "z[156,5]", "X": 1}, { "VarName": "z[157,8]", "X": 1}, { "VarName": "z[158,9]", "X": 1}, { "VarName": "z[159,3]", "X": 1}, { "VarName": "z[160,8]", "X": 1}, { "VarName": "z[161,7]", "X": 1}, { "VarName": "z[162,4]", "X": 1}, { "VarName": "z[163,9]", "X": 1}, { "VarName": "z[164,8]", "X": 1}, { "VarName": "z[165,5]", "X": 1}, { "VarName": "z[166,0]", "X": 1}, { "VarName": "z[167,6]", "X": 1}, { "VarName": "z[168,9]", "X": 1}, { "VarName": "z[169,9]", "X": 1}, { "VarName": "z[170,4]", "X": 1}, { "VarName": "z[171,7]", "X": 1}, { "VarName": "z[172,5]", "X": 1}, { "VarName": "z[173,9]", "X": 1}, { "VarName": "z[174,6]", "X": 1}, { "VarName": "z[175,5]", "X": 1}, { "VarName": "z[176,1]", "X": 1}, { "VarName": "z[177,5]", "X": 1}, { "VarName": "z[178,2]", "X": 1}, { "VarName": "z[179,9]", "X": 1}, { "VarName": "z[180,5]", "X": 1}, { "VarName": "z[181,7]", "X": 1}, { "VarName": "z[182,8]", "X": 1}, { "VarName": "z[183,8]", "X": 1}, { "VarName": "z[184,5]", "X": 1}, { "VarName": "z[185,6]", "X": 1}, { "VarName": "z[186,7]", "X": 1}, { "VarName": "z[187,3]", "X": 1}, { "VarName": "z[188,7]", "X": 1}, { "VarName": "z[189,5]", "X": 1}, { "VarName": "z[190,1]", "X": 1}, { "VarName": "z[191,5]", "X": 1}, { "VarName": "z[192,6]", "X": 1}, { "VarName": "z[193,7]", "X": 1}, { "VarName": "z[194,3]", "X": 1}, { "VarName": "z[195,5]", "X": 1}, { "VarName": "z[196,1]", "X": 1}, { "VarName": "z[197,0]", "X": 1}, { "VarName": "z[198,7]", "X": 1}, { "VarName": "z[199,8]", "X": 1}, { "VarName": "z[200,7]", "X": 1}, { "VarName": "z[201,6]", "X": 1}, { "VarName": "z[202,1]", "X": 1}, { "VarName": "z[203,0]", "X": 1}, { "VarName": "z[204,6]", "X": 1}, { "VarName": "z[205,5]", "X": 1}, { "VarName": "z[206,3]", "X": 1}, { "VarName": "z[207,0]", "X": 1}, { "VarName": "z[208,6]", "X": 1}, { "VarName": "z[209,5]", "X": 1}, { "VarName": "z[210,5]", "X": 1}, { "VarName": "z[211,8]", "X": 1}, { "VarName": "z[212,9]", "X": 1}, { "VarName": "z[213,8]", "X": 1}, { "VarName": "z[214,4]", "X": 1}, { "VarName": "z[215,9]", "X": 1}, { "VarName": "z[216,5]", "X": 1}, { "VarName": "z[217,7]", "X": 1}, { "VarName": "z[218,5]", "X": 1}, { "VarName": "z[219,7]", "X": 1}]}