{ "SolutionInfo": { "Status": 2, "Runtime": 1.1899995803833008e-01, "Work": 9.7289661680205988e-02, "ObjVal": 300778, "ObjBound": 300778, "ObjBoundC": 300778, "MIPGap": 0, "IntVio": 0, "BoundVio": 0, "ConstrVio": 0, "IterCount": 743, "BarIterCount": 0, "NodeCount": 1, "SolCount": 2, "PoolObjBound": 300778, "PoolObjVal": [ 300778, 300119]}, "Vars": [ { "VarName": "x[0]", "X": 1}, { "VarName": "x[1]", "X": 1}, { "VarName": "x[2]", "X": 1}, { "VarName": "x[3]", "X": 1}, { "VarName": "x[4]", "X": 1}, { "VarName": "x[5]", "X": 1}, { "VarName": "x[6]", "X": 1}, { "VarName": "x[7]", "X": 1}, { "VarName": "x[8]", "X": 1}, { "VarName": "x[9]", "X": 1}, { "VarName": "x[10]", "X": 1}, { "VarName": "x[11]", "X": 1}, { "VarName": "x[12]", "X": 1}, { "VarName": "x[13]", "X": 1}, { "VarName": "x[14]", "X": 1}, { "VarName": "x[15]", "X": 1}, { "VarName": "x[16]", "X": 1}, { "VarName": "x[17]", "X": 1}, { "VarName": "x[18]", "X": 1}, { "VarName": "x[19]", "X": 1}, { "VarName": "x[20]", "X": 1}, { "VarName": "x[21]", "X": 1}, { "VarName": "x[22]", "X": 1}, { "VarName": "x[23]", "X": 1}, { "VarName": "x[24]", "X": 1}, { "VarName": "x[25]", "X": 1}, { "VarName": "x[26]", "X": 1}, { "VarName": "x[27]", "X": 1}, { "VarName": "x[28]", "X": 1}, { "VarName": "x[29]", "X": 1}, { "VarName": "x[30]", "X": 1}, { "VarName": "x[31]", "X": 1}, { "VarName": "x[32]", "X": 1}, { "VarName": "x[33]", "X": 1}, { "VarName": "x[34]", "X": 1}, { "VarName": "x[35]", "X": 1}, { "VarName": "x[36]", "X": 1}, { "VarName": "x[37]", "X": 1}, { "VarName": "x[38]", "X": 1}, { "VarName": "x[39]", "X": 1}, { "VarName": "x[40]", "X": 1}, { "VarName": "x[41]", "X": 1}, { "VarName": "x[42]", "X": 1}, { "VarName": "x[43]", "X": 1}, { "VarName": "x[44]", "X": 1}, { "VarName": "x[45]", "X": 1}, { "VarName": "x[46]", "X": 1}, { "VarName": "x[47]", "X": 1}, { "VarName": "x[48]", "X": 1}, { "VarName": "x[49]", "X": 1}, { "VarName": "x[50]", "X": 1}, { "VarName": "x[51]", "X": 1}, { "VarName": "x[52]", "X": 1}, { "VarName": "x[53]", "X": 1}, { "VarName": "x[54]", "X": 1}, { "VarName": "y[0,0]", "X": 1}, { "VarName": "y[1,0]", "X": 1}, { "VarName": "y[2,0]", "X": 1}, { "VarName": "y[3,0]", "X": 1}, { "VarName": "y[4,0]", "X": 1}, { "VarName": "y[5,0]", "X": 1}, { "VarName": "y[6,0]", "X": 1}, { "VarName": "y[7,4]", "X": 1}, { "VarName": "y[8,4]", "X": 1}, { "VarName": "y[9,4]", "X": 1}, { "VarName": "y[10,4]", "X": 1}, { "VarName": "y[11,4]", "X": 1}, { "VarName": "y[12,4]", "X": 1}, { "VarName": "y[13,4]", "X": 1}, { "VarName": "y[14,4]", "X": 1}, { "VarName": "y[15,4]", "X": 1}, { "VarName": "y[16,0]", "X": 1}, { "VarName": "y[17,0]", "X": 1}, { "VarName": "y[18,0]", "X": 1}, { "VarName": "y[19,0]", "X": 1}, { "VarName": "y[20,0]", "X": 1}, { "VarName": "y[21,0]", "X": 1}, { "VarName": "y[22,0]", "X": 1}, { "VarName": "y[23,0]", "X": 1}, { "VarName": "y[24,0]", "X": 1}, { "VarName": "y[25,0]", "X": 1}, { "VarName": "y[26,0]", "X": 1}, { "VarName": "y[27,0]", "X": 1}, { "VarName": "y[28,0]", "X": 1}, { "VarName": "y[29,0]", "X": 1}, { "VarName": "y[30,0]", "X": 1}, { "VarName": "y[31,0]", "X": 1}, { "VarName": "y[32,0]", "X": 1}, { "VarName": "y[33,0]", "X": 1}, { "VarName": "y[34,0]", "X": 1}, { "VarName": "y[35,0]", "X": 1}, { "VarName": "y[36,0]", "X": 1}, { "VarName": "y[37,0]", "X": 1}, { "VarName": "y[38,0]", "X": 1}, { "VarName": "y[39,0]", "X": 1}, { "VarName": "y[40,0]", "X": 1}, { "VarName": "y[41,0]", "X": 1}, { "VarName": "y[42,0]", "X": 1}, { "VarName": "y[43,0]", "X": 1}, { "VarName": "y[44,7]", "X": 1}, { "VarName": "y[45,7]", "X": 1}, { "VarName": "y[46,7]", "X": 1}, { "VarName": "y[47,7]", "X": 1}, { "VarName": "y[48,7]", "X": 1}, { "VarName": "y[49,7]", "X": 1}, { "VarName": "y[50,7]", "X": 1}, { "VarName": "y[51,7]", "X": 1}, { "VarName": "y[52,9]", "X": 1}, { "VarName": "y[53,9]", "X": 1}, { "VarName": "y[54,9]", "X": 1}, { "VarName": "y[55,9]", "X": 1}, { "VarName": "y[56,9]", "X": 1}, { "VarName": "y[57,9]", "X": 1}, { "VarName": "y[58,6]", "X": 1}, { "VarName": "y[59,6]", "X": 1}, { "VarName": "y[60,6]", "X": 1}, { "VarName": "y[61,6]", "X": 1}, { "VarName": "y[62,6]", "X": 1}, { "VarName": "y[63,6]", "X": 1}, { "VarName": "y[64,6]", "X": 1}, { "VarName": "y[65,6]", "X": 1}, { "VarName": "y[66,6]", "X": 1}, { "VarName": "y[67,3]", "X": 1}, { "VarName": "y[68,3]", "X": 1}, { "VarName": "y[69,3]", "X": 1}, { "VarName": "y[70,3]", "X": 1}, { "VarName": "y[71,3]", "X": 1}, { "VarName": "y[72,3]", "X": 1}, { "VarName": "y[73,3]", "X": 1}, { "VarName": "y[74,3]", "X": 1}, { "VarName": "y[75,12]", "X": 1}, { "VarName": "y[76,12]", "X": 1}, { "VarName": "y[77,12]", "X": 1}, { "VarName": "y[78,12]", "X": 1}, { "VarName": "y[79,12]", "X": 1}, { "VarName": "y[80,12]", "X": 1}, { "VarName": "y[81,12]", "X": 1}, { "VarName": "y[82,12]", "X": 1}, { "VarName": "y[83,12]", "X": 1}, { "VarName": "y[84,12]", "X": 1}, { "VarName": "y[85,12]", "X": 1}, { "VarName": "y[86,12]", "X": 1}, { "VarName": "y[87,12]", "X": 1}, { "VarName": "y[88,12]", "X": 1}, { "VarName": "y[89,3]", "X": 1}, { "VarName": "y[90,3]", "X": 1}, { "VarName": "y[91,3]", "X": 1}, { "VarName": "y[92,3]", "X": 1}, { "VarName": "y[93,3]", "X": 1}, { "VarName": "y[94,3]", "X": 1}, { "VarName": "y[95,3]", "X": 1}, { "VarName": "y[96,3]", "X": 1}, { "VarName": "y[97,11]", "X": 1}, { "VarName": "y[98,11]", "X": 1}, { "VarName": "y[99,11]", "X": 1}, { "VarName": "y[100,11]", "X": 1}, { "VarName": "y[101,11]", "X": 1}, { "VarName": "y[102,8]", "X": 1}, { "VarName": "y[103,8]", "X": 1}, { "VarName": "y[104,8]", "X": 1}, { "VarName": "y[105,8]", "X": 1}, { "VarName": "y[106,8]", "X": 1}, { "VarName": "y[107,8]", "X": 1}, { "VarName": "y[108,6]", "X": 1}, { "VarName": "y[109,6]", "X": 1}, { "VarName": "y[110,6]", "X": 1}, { "VarName": "y[111,6]", "X": 1}, { "VarName": "y[112,6]", "X": 1}, { "VarName": "y[113,6]", "X": 1}, { "VarName": "y[114,6]", "X": 1}, { "VarName": "y[115,9]", "X": 1}, { "VarName": "y[116,9]", "X": 1}, { "VarName": "y[117,9]", "X": 1}, { "VarName": "y[118,9]", "X": 1}, { "VarName": "y[119,9]", "X": 1}, { "VarName": "y[120,9]", "X": 1}, { "VarName": "y[121,9]", "X": 1}, { "VarName": "y[122,9]", "X": 1}, { "VarName": "y[123,9]", "X": 1}, { "VarName": "y[124,9]", "X": 1}, { "VarName": "y[125,4]", "X": 1}, { "VarName": "y[126,4]", "X": 1}, { "VarName": "y[127,4]", "X": 1}, { "VarName": "y[128,4]", "X": 1}, { "VarName": "y[129,4]", "X": 1}, { "VarName": "y[130,4]", "X": 1}, { "VarName": "y[131,4]", "X": 1}, { "VarName": "y[132,4]", "X": 1}, { "VarName": "y[133,4]", "X": 1}, { "VarName": "y[134,11]", "X": 1}, { "VarName": "y[135,11]", "X": 1}, { "VarName": "y[136,11]", "X": 1}, { "VarName": "y[137,11]", "X": 1}, { "VarName": "y[138,11]", "X": 1}, { "VarName": "y[139,11]", "X": 1}, { "VarName": "y[140,11]", "X": 1}, { "VarName": "y[141,11]", "X": 1}, { "VarName": "y[142,11]", "X": 1}, { "VarName": "y[143,12]", "X": 1}, { "VarName": "y[144,12]", "X": 1}, { "VarName": "y[145,12]", "X": 1}, { "VarName": "y[146,12]", "X": 1}, { "VarName": "y[147,12]", "X": 1}, { "VarName": "y[148,12]", "X": 1}, { "VarName": "y[149,6]", "X": 1}, { "VarName": "y[150,6]", "X": 1}, { "VarName": "y[151,6]", "X": 1}, { "VarName": "y[152,6]", "X": 1}, { "VarName": "y[153,6]", "X": 1}, { "VarName": "y[154,10]", "X": 1}, { "VarName": "y[155,10]", "X": 1}, { "VarName": "y[156,10]", "X": 1}, { "VarName": "y[157,10]", "X": 1}, { "VarName": "y[158,10]", "X": 1}, { "VarName": "y[159,10]", "X": 1}, { "VarName": "y[160,10]", "X": 1}, { "VarName": "y[161,10]", "X": 1}, { "VarName": "y[162,10]", "X": 1}, { "VarName": "y[163,10]", "X": 1}, { "VarName": "y[164,10]", "X": 1}, { "VarName": "y[165,10]", "X": 1}, { "VarName": "y[166,10]", "X": 1}, { "VarName": "y[167,10]", "X": 1}, { "VarName": "y[168,10]", "X": 1}, { "VarName": "y[169,10]", "X": 1}, { "VarName": "y[170,10]", "X": 1}, { "VarName": "y[171,14]", "X": 1}, { "VarName": "y[172,14]", "X": 1}, { "VarName": "y[173,14]", "X": 1}, { "VarName": "y[174,14]", "X": 1}, { "VarName": "y[175,14]", "X": 1}, { "VarName": "y[176,14]", "X": 1}, { "VarName": "y[177,14]", "X": 1}, { "VarName": "y[178,14]", "X": 1}, { "VarName": "y[179,5]", "X": 1}, { "VarName": "y[180,5]", "X": 1}, { "VarName": "y[181,5]", "X": 1}, { "VarName": "y[182,5]", "X": 1}, { "VarName": "y[183,5]", "X": 1}, { "VarName": "y[184,3]", "X": 1}, { "VarName": "y[185,3]", "X": 1}, { "VarName": "y[186,3]", "X": 1}, { "VarName": "y[187,3]", "X": 1}, { "VarName": "y[188,3]", "X": 1}, { "VarName": "y[189,3]", "X": 1}, { "VarName": "y[190,11]", "X": 1}, { "VarName": "y[191,11]", "X": 1}, { "VarName": "y[192,11]", "X": 1}, { "VarName": "y[193,11]", "X": 1}, { "VarName": "y[194,11]", "X": 1}, { "VarName": "y[195,11]", "X": 1}, { "VarName": "y[196,11]", "X": 1}, { "VarName": "y[197,7]", "X": 1}, { "VarName": "y[198,7]", "X": 1}, { "VarName": "y[199,7]", "X": 1}, { "VarName": "y[200,7]", "X": 1}, { "VarName": "y[201,7]", "X": 1}, { "VarName": "y[202,7]", "X": 1}, { "VarName": "y[203,7]", "X": 1}, { "VarName": "y[204,9]", "X": 1}, { "VarName": "y[205,9]", "X": 1}, { "VarName": "y[206,9]", "X": 1}, { "VarName": "y[207,9]", "X": 1}, { "VarName": "y[208,9]", "X": 1}, { "VarName": "y[209,9]", "X": 1}, { "VarName": "y[210,9]", "X": 1}, { "VarName": "y[211,9]", "X": 1}, { "VarName": "y[212,9]", "X": 1}, { "VarName": "y[213,9]", "X": 1}, { "VarName": "y[214,13]", "X": 1}, { "VarName": "y[215,13]", "X": 1}, { "VarName": "y[216,13]", "X": 1}, { "VarName": "y[217,13]", "X": 1}, { "VarName": "y[218,13]", "X": 1}, { "VarName": "y[219,13]", "X": 1}, { "VarName": "y[220,13]", "X": 1}, { "VarName": "y[221,13]", "X": 1}, { "VarName": "y[222,9]", "X": 1}, { "VarName": "y[223,9]", "X": 1}, { "VarName": "y[224,9]", "X": 1}, { "VarName": "y[225,9]", "X": 1}, { "VarName": "y[226,9]", "X": 1}, { "VarName": "y[227,9]", "X": 1}, { "VarName": "y[228,9]", "X": 1}, { "VarName": "y[229,12]", "X": 1}, { "VarName": "y[230,12]", "X": 1}, { "VarName": "y[231,12]", "X": 1}, { "VarName": "y[232,12]", "X": 1}, { "VarName": "y[233,12]", "X": 1}, { "VarName": "y[234,12]", "X": 1}, { "VarName": "y[235,12]", "X": 1}, { "VarName": "y[236,13]", "X": 1}, { "VarName": "y[237,13]", "X": 1}, { "VarName": "y[238,13]", "X": 1}, { "VarName": "y[239,13]", "X": 1}, { "VarName": "y[240,13]", "X": 1}, { "VarName": "y[241,13]", "X": 1}, { "VarName": "y[242,13]", "X": 1}, { "VarName": "y[243,13]", "X": 1}, { "VarName": "y[244,13]", "X": 1}, { "VarName": "y[245,13]", "X": 1}, { "VarName": "y[246,1]", "X": 1}, { "VarName": "y[247,1]", "X": 1}, { "VarName": "y[248,1]", "X": 1}, { "VarName": "y[249,1]", "X": 1}, { "VarName": "y[250,1]", "X": 1}, { "VarName": "y[251,1]", "X": 1}, { "VarName": "y[252,3]", "X": 1}, { "VarName": "y[253,3]", "X": 1}, { "VarName": "y[254,3]", "X": 1}, { "VarName": "y[255,3]", "X": 1}, { "VarName": "y[256,3]", "X": 1}, { "VarName": "y[257,3]", "X": 1}, { "VarName": "y[258,3]", "X": 1}, { "VarName": "y[259,3]", "X": 1}, { "VarName": "y[260,6]", "X": 1}, { "VarName": "y[261,6]", "X": 1}, { "VarName": "y[262,6]", "X": 1}, { "VarName": "y[263,6]", "X": 1}, { "VarName": "y[264,6]", "X": 1}, { "VarName": "y[265,6]", "X": 1}, { "VarName": "y[266,6]", "X": 1}, { "VarName": "y[267,12]", "X": 1}, { "VarName": "y[268,12]", "X": 1}, { "VarName": "y[269,12]", "X": 1}, { "VarName": "y[270,12]", "X": 1}, { "VarName": "y[271,12]", "X": 1}, { "VarName": "y[272,12]", "X": 1}, { "VarName": "y[273,12]", "X": 1}, { "VarName": "y[274,10]", "X": 1}, { "VarName": "y[275,10]", "X": 1}, { "VarName": "y[276,10]", "X": 1}, { "VarName": "y[277,10]", "X": 1}, { "VarName": "y[278,10]", "X": 1}, { "VarName": "y[279,10]", "X": 1}, { "VarName": "y[280,10]", "X": 1}, { "VarName": "y[281,10]", "X": 1}, { "VarName": "y[282,10]", "X": 1}, { "VarName": "y[283,10]", "X": 1}, { "VarName": "y[284,11]", "X": 1}, { "VarName": "y[285,11]", "X": 1}, { "VarName": "y[286,11]", "X": 1}, { "VarName": "y[287,11]", "X": 1}, { "VarName": "y[288,11]", "X": 1}, { "VarName": "y[289,11]", "X": 1}, { "VarName": "y[290,11]", "X": 1}, { "VarName": "y[291,11]", "X": 1}, { "VarName": "y[292,11]", "X": 1}, { "VarName": "y[293,11]", "X": 1}, { "VarName": "y[294,11]", "X": 1}, { "VarName": "y[295,11]", "X": 1}, { "VarName": "y[296,11]", "X": 1}, { "VarName": "y[297,7]", "X": 1}, { "VarName": "y[298,7]", "X": 1}, { "VarName": "y[299,7]", "X": 1}, { "VarName": "y[300,7]", "X": 1}, { "VarName": "y[301,7]", "X": 1}, { "VarName": "y[302,10]", "X": 1}, { "VarName": "y[303,10]", "X": 1}, { "VarName": "y[304,10]", "X": 1}, { "VarName": "y[305,10]", "X": 1}, { "VarName": "y[306,10]", "X": 1}, { "VarName": "y[307,10]", "X": 1}, { "VarName": "y[308,10]", "X": 1}, { "VarName": "y[309,13]", "X": 1}, { "VarName": "y[310,13]", "X": 1}, { "VarName": "y[311,13]", "X": 1}, { "VarName": "y[312,13]", "X": 1}, { "VarName": "y[313,13]", "X": 1}, { "VarName": "y[314,13]", "X": 1}, { "VarName": "y[315,13]", "X": 1}, { "VarName": "y[316,13]", "X": 1}, { "VarName": "y[317,4]", "X": 1}, { "VarName": "y[318,4]", "X": 1}, { "VarName": "y[319,4]", "X": 1}, { "VarName": "y[320,4]", "X": 1}, { "VarName": "y[321,4]", "X": 1}, { "VarName": "y[322,10]", "X": 1}, { "VarName": "y[323,10]", "X": 1}, { "VarName": "y[324,10]", "X": 1}, { "VarName": "y[325,10]", "X": 1}, { "VarName": "y[326,10]", "X": 1}, { "VarName": "y[327,10]", "X": 1}, { "VarName": "y[328,10]", "X": 1}, { "VarName": "y[329,10]", "X": 1}, { "VarName": "y[330,4]", "X": 1}, { "VarName": "y[331,4]", "X": 1}, { "VarName": "y[332,4]", "X": 1}, { "VarName": "y[333,4]", "X": 1}, { "VarName": "y[334,4]", "X": 1}, { "VarName": "y[335,4]", "X": 1}, { "VarName": "y[336,4]", "X": 1}, { "VarName": "y[337,4]", "X": 1}, { "VarName": "y[338,4]", "X": 1}, { "VarName": "y[339,1]", "X": 1}, { "VarName": "y[340,1]", "X": 1}, { "VarName": "y[341,1]", "X": 1}, { "VarName": "y[342,1]", "X": 1}, { "VarName": "y[343,1]", "X": 1}, { "VarName": "y[344,4]", "X": 1}, { "VarName": "y[345,4]", "X": 1}, { "VarName": "y[346,4]", "X": 1}, { "VarName": "y[347,4]", "X": 1}, { "VarName": "y[348,4]", "X": 1}, { "VarName": "y[349,4]", "X": 1}, { "VarName": "y[350,8]", "X": 1}, { "VarName": "y[351,8]", "X": 1}, { "VarName": "y[352,8]", "X": 1}, { "VarName": "y[353,8]", "X": 1}, { "VarName": "y[354,8]", "X": 1}, { "VarName": "y[355,8]", "X": 1}, { "VarName": "y[356,8]", "X": 1}, { "VarName": "y[357,8]", "X": 1}, { "VarName": "y[358,8]", "X": 1}, { "VarName": "y[359,8]", "X": 1}, { "VarName": "y[360,2]", "X": 1}, { "VarName": "y[361,2]", "X": 1}, { "VarName": "y[362,2]", "X": 1}, { "VarName": "y[363,2]", "X": 1}, { "VarName": "y[364,2]", "X": 1}, { "VarName": "y[365,2]", "X": 1}, { "VarName": "y[366,2]", "X": 1}, { "VarName": "y[367,2]", "X": 1}, { "VarName": "y[368,2]", "X": 1}, { "VarName": "y[369,2]", "X": 1}, { "VarName": "y[370,2]", "X": 1}, { "VarName": "y[371,2]", "X": 1}, { "VarName": "y[372,2]", "X": 1}, { "VarName": "y[373,2]", "X": 1}, { "VarName": "y[374,2]", "X": 1}, { "VarName": "y[375,4]", "X": 1}, { "VarName": "y[376,4]", "X": 1}, { "VarName": "y[377,4]", "X": 1}, { "VarName": "y[378,4]", "X": 1}, { "VarName": "y[379,4]", "X": 1}, { "VarName": "y[380,9]", "X": 1}, { "VarName": "y[381,9]", "X": 1}, { "VarName": "y[382,9]", "X": 1}, { "VarName": "y[383,9]", "X": 1}, { "VarName": "y[384,9]", "X": 1}, { "VarName": "y[385,8]", "X": 1}, { "VarName": "y[386,8]", "X": 1}, { "VarName": "y[387,8]", "X": 1}, { "VarName": "y[388,8]", "X": 1}, { "VarName": "y[389,8]", "X": 1}, { "VarName": "y[390,8]", "X": 1}, { "VarName": "y[391,8]", "X": 1}, { "VarName": "y[392,8]", "X": 1}, { "VarName": "y[393,0]", "X": 1}, { "VarName": "y[394,0]", "X": 1}, { "VarName": "y[395,0]", "X": 1}, { "VarName": "y[396,0]", "X": 1}, { "VarName": "y[397,0]", "X": 1}, { "VarName": "z[0,0]", "X": 1}, { "VarName": "z[1,4]", "X": 1}, { "VarName": "z[2,0]", "X": 1}, { "VarName": "z[3,0]", "X": 1}, { "VarName": "z[4,0]", "X": 1}, { "VarName": "z[5,0]", "X": 1}, { "VarName": "z[6,7]", "X": 1}, { "VarName": "z[7,9]", "X": 1}, { "VarName": "z[8,6]", "X": 1}, { "VarName": "z[9,3]", "X": 1}, { "VarName": "z[10,12]", "X": 1}, { "VarName": "z[11,12]", "X": 1}, { "VarName": "z[12,3]", "X": 1}, { "VarName": "z[13,11]", "X": 1}, { "VarName": "z[14,8]", "X": 1}, { "VarName": "z[15,6]", "X": 1}, { "VarName": "z[16,9]", "X": 1}, { "VarName": "z[17,4]", "X": 1}, { "VarName": "z[18,11]", "X": 1}, { "VarName": "z[19,12]", "X": 1}, { "VarName": "z[20,6]", "X": 1}, { "VarName": "z[21,10]", "X": 1}, { "VarName": "z[22,10]", "X": 1}, { "VarName": "z[23,14]", "X": 1}, { "VarName": "z[24,5]", "X": 1}, { "VarName": "z[25,3]", "X": 1}, { "VarName": "z[26,11]", "X": 1}, { "VarName": "z[27,7]", "X": 1}, { "VarName": "z[28,9]", "X": 1}, { "VarName": "z[29,13]", "X": 1}, { "VarName": "z[30,9]", "X": 1}, { "VarName": "z[31,12]", "X": 1}, { "VarName": "z[32,13]", "X": 1}, { "VarName": "z[33,1]", "X": 1}, { "VarName": "z[34,3]", "X": 1}, { "VarName": "z[35,6]", "X": 1}, { "VarName": "z[36,12]", "X": 1}, { "VarName": "z[37,10]", "X": 1}, { "VarName": "z[38,11]", "X": 1}, { "VarName": "z[39,11]", "X": 1}, { "VarName": "z[40,7]", "X": 1}, { "VarName": "z[41,10]", "X": 1}, { "VarName": "z[42,13]", "X": 1}, { "VarName": "z[43,4]", "X": 1}, { "VarName": "z[44,10]", "X": 1}, { "VarName": "z[45,4]", "X": 1}, { "VarName": "z[46,1]", "X": 1}, { "VarName": "z[47,4]", "X": 1}, { "VarName": "z[48,8]", "X": 1}, { "VarName": "z[49,2]", "X": 1}, { "VarName": "z[50,2]", "X": 1}, { "VarName": "z[51,4]", "X": 1}, { "VarName": "z[52,9]", "X": 1}, { "VarName": "z[53,8]", "X": 1}, { "VarName": "z[54,0]", "X": 1}]}